// class version 52.0 (52)
// access flags 0x421
public abstract class cofh/asmhooks/world/WorldServerProxy extends net/minecraft/world/WorldServer  {

  // compiled from: WorldServerProxy.java

  // access flags 0x4
  protected Lnet/minecraft/world/WorldServer; proxiedWorld

  // access flags 0xA
  private static getWorldName(Lnet/minecraft/world/World;)Ljava/lang/String;
   L0
    LINENUMBER 15 L0
    ALOAD 0
    INVOKEVIRTUAL net/minecraft/world/World.func_72912_H ()Lnet/minecraft/world/storage/WorldInfo;
    INVOKEVIRTUAL net/minecraft/world/storage/WorldInfo.func_76065_j ()Ljava/lang/String;
    ARETURN
   L1
    LOCALVARIABLE world Lnet/minecraft/world/World; L0 L1 0
    MAXSTACK = 1
    MAXLOCALS = 1

  // access flags 0xA
  private static getWorldSettings(Lnet/minecraft/world/World;)Lnet/minecraft/world/WorldSettings;
   L0
    LINENUMBER 20 L0
    NEW net/minecraft/world/WorldSettings
    DUP
    ALOAD 0
    INVOKEVIRTUAL net/minecraft/world/World.func_72912_H ()Lnet/minecraft/world/storage/WorldInfo;
    INVOKESPECIAL net/minecraft/world/WorldSettings.<init> (Lnet/minecraft/world/storage/WorldInfo;)V
    ARETURN
   L1
    LOCALVARIABLE world Lnet/minecraft/world/World; L0 L1 0
    MAXSTACK = 3
    MAXLOCALS = 1

  // access flags 0x1
  public <init>(Lnet/minecraft/world/WorldServer;)V
   L0
    LINENUMBER 25 L0
    ALOAD 0
    ALOAD 1
    INVOKEVIRTUAL net/minecraft/world/WorldServer.func_73046_m ()Lnet/minecraft/server/MinecraftServer;
    ALOAD 1
    INVOKEVIRTUAL net/minecraft/world/WorldServer.func_72860_G ()Lnet/minecraft/world/storage/ISaveHandler;
    ALOAD 1
    INVOKEVIRTUAL net/minecraft/world/WorldServer.func_72912_H ()Lnet/minecraft/world/storage/WorldInfo;
    ALOAD 1
    GETFIELD net/minecraft/world/WorldServer.field_73011_w : Lnet/minecraft/world/WorldProvider;
    ALOAD 1
    GETFIELD net/minecraft/world/WorldServer.field_72984_F : Lnet/minecraft/profiler/Profiler;
    ALOAD 1
    GETFIELD net/minecraft/world/WorldServer.field_72995_K : Z
    INVOKESPECIAL net/minecraft/world/WorldServer.<init> (Lnet/minecraft/server/MinecraftServer;Lnet/minecraft/world/storage/ISaveHandler;Lnet/minecraft/world/storage/WorldInfo;Lnet/minecraft/world/WorldProvider;Lnet/minecraft/profiler/Profiler;Z)V
   L1
    LINENUMBER 26 L1
    ALOAD 0
    ALOAD 1
    PUTFIELD cofh/asmhooks/world/WorldServerProxy.proxiedWorld : Lnet/minecraft/world/WorldServer;
   L2
    LINENUMBER 28 L2
    LDC Lnet/minecraft/world/World;.class
    ALOAD 0
    ALOAD 1
    INVOKEVIRTUAL net/minecraft/world/WorldServer.getPerWorldStorage ()Lnet/minecraft/world/storage/MapStorage;
    ICONST_1
    ANEWARRAY java/lang/String
    DUP
    ICONST_0
    LDC "perWorldStorage"
    AASTORE
    INVOKESTATIC net/minecraftforge/fml/relauncher/ReflectionHelper.setPrivateValue (Ljava/lang/Class;Ljava/lang/Object;Ljava/lang/Object;[Ljava/lang/String;)V
   L3
    LINENUMBER 29 L3
    LDC Lnet/minecraft/world/World;.class
    ALOAD 0
    ALOAD 1
    GETFIELD net/minecraft/world/WorldServer.capturedBlockSnapshots : Ljava/util/ArrayList;
    ICONST_1
    ANEWARRAY java/lang/String
    DUP
    ICONST_0
    LDC "capturedBlockSnapshots"
    AASTORE
    INVOKESTATIC net/minecraftforge/fml/relauncher/ReflectionHelper.setPrivateValue (Ljava/lang/Class;Ljava/lang/Object;Ljava/lang/Object;[Ljava/lang/String;)V
   L4
    LINENUMBER 30 L4
    LDC Lnet/minecraft/world/World;.class
    ALOAD 0
    ALOAD 1
    GETFIELD net/minecraft/world/WorldServer.field_72996_f : Ljava/util/List;
    ICONST_2
    ANEWARRAY java/lang/String
    DUP
    ICONST_0
    LDC "field_72996_f"
    AASTORE
    DUP
    ICONST_1
    LDC "loadedEntityList"
    AASTORE
    INVOKESTATIC net/minecraftforge/fml/relauncher/ReflectionHelper.setPrivateValue (Ljava/lang/Class;Ljava/lang/Object;Ljava/lang/Object;[Ljava/lang/String;)V
   L5
    LINENUMBER 31 L5
    LDC Lnet/minecraft/world/World;.class
    ALOAD 0
    ALOAD 1
    GETFIELD net/minecraft/world/WorldServer.field_147482_g : Ljava/util/List;
    ICONST_2
    ANEWARRAY java/lang/String
    DUP
    ICONST_0
    LDC "field_147482_g"
    AASTORE
    DUP
    ICONST_1
    LDC "loadedTileEntityList"
    AASTORE
    INVOKESTATIC net/minecraftforge/fml/relauncher/ReflectionHelper.setPrivateValue (Ljava/lang/Class;Ljava/lang/Object;Ljava/lang/Object;[Ljava/lang/String;)V
   L6
    LINENUMBER 32 L6
    LDC Lnet/minecraft/world/World;.class
    ALOAD 0
    ALOAD 1
    GETFIELD net/minecraft/world/WorldServer.field_73010_i : Ljava/util/List;
    ICONST_2
    ANEWARRAY java/lang/String
    DUP
    ICONST_0
    LDC "field_73010_i"
    AASTORE
    DUP
    ICONST_1
    LDC "playerEntities"
    AASTORE
    INVOKESTATIC net/minecraftforge/fml/relauncher/ReflectionHelper.setPrivateValue (Ljava/lang/Class;Ljava/lang/Object;Ljava/lang/Object;[Ljava/lang/String;)V
   L7
    LINENUMBER 33 L7
    LDC Lnet/minecraft/world/World;.class
    ALOAD 0
    ALOAD 1
    GETFIELD net/minecraft/world/WorldServer.field_73007_j : Ljava/util/List;
    ICONST_2
    ANEWARRAY java/lang/String
    DUP
    ICONST_0
    LDC "field_73007_j"
    AASTORE
    DUP
    ICONST_1
    LDC "weatherEffects"
    AASTORE
    INVOKESTATIC net/minecraftforge/fml/relauncher/ReflectionHelper.setPrivateValue (Ljava/lang/Class;Ljava/lang/Object;Ljava/lang/Object;[Ljava/lang/String;)V
   L8
    LINENUMBER 34 L8
    LDC Lnet/minecraft/world/World;.class
    ALOAD 0
    ALOAD 1
    GETFIELD net/minecraft/world/WorldServer.field_73011_w : Lnet/minecraft/world/WorldProvider;
    ICONST_2
    ANEWARRAY java/lang/String
    DUP
    ICONST_0
    LDC "field_73011_w"
    AASTORE
    DUP
    ICONST_1
    LDC "provider"
    AASTORE
    INVOKESTATIC net/minecraftforge/fml/relauncher/ReflectionHelper.setPrivateValue (Ljava/lang/Class;Ljava/lang/Object;Ljava/lang/Object;[Ljava/lang/String;)V
   L9
    LINENUMBER 35 L9
    LDC Lnet/minecraft/world/World;.class
    ALOAD 0
    ALOAD 1
    GETFIELD net/minecraft/world/WorldServer.field_73012_v : Ljava/util/Random;
    ICONST_2
    ANEWARRAY java/lang/String
    DUP
    ICONST_0
    LDC "field_73012_v"
    AASTORE
    DUP
    ICONST_1
    LDC "rand"
    AASTORE
    INVOKESTATIC net/minecraftforge/fml/relauncher/ReflectionHelper.setPrivateValue (Ljava/lang/Class;Ljava/lang/Object;Ljava/lang/Object;[Ljava/lang/String;)V
   L10
    LINENUMBER 37 L10
    ALOAD 0
    ALOAD 1
    INVOKEVIRTUAL net/minecraft/world/WorldServer.func_175693_T ()Lnet/minecraft/world/storage/MapStorage;
    PUTFIELD cofh/asmhooks/world/WorldServerProxy.field_72988_C : Lnet/minecraft/world/storage/MapStorage;
   L11
    LINENUMBER 38 L11
    ALOAD 0
    INVOKEVIRTUAL cofh/asmhooks/world/WorldServerProxy.cofh_updateProps ()V
   L12
    LINENUMBER 39 L12
    RETURN
   L13
    LOCALVARIABLE this Lcofh/asmhooks/world/WorldServerProxy; L0 L13 0
    LOCALVARIABLE world Lnet/minecraft/world/WorldServer; L0 L13 1
    MAXSTACK = 7
    MAXLOCALS = 2

  // access flags 0x4
  protected cofh_updateProps()V
   L0
    LINENUMBER 43 L0
    ALOAD 0
    ALOAD 0
    GETFIELD cofh/asmhooks/world/WorldServerProxy.proxiedWorld : Lnet/minecraft/world/WorldServer;
    GETFIELD net/minecraft/world/WorldServer.field_72999_e : Z
    PUTFIELD cofh/asmhooks/world/WorldServerProxy.field_72999_e : Z
   L1
    LINENUMBER 44 L1
    ALOAD 0
    ALOAD 0
    GETFIELD cofh/asmhooks/world/WorldServerProxy.proxiedWorld : Lnet/minecraft/world/WorldServer;
    GETFIELD net/minecraft/world/WorldServer.field_73008_k : I
    PUTFIELD cofh/asmhooks/world/WorldServerProxy.field_73008_k : I
   L2
    LINENUMBER 45 L2
    ALOAD 0
    ALOAD 0
    GETFIELD cofh/asmhooks/world/WorldServerProxy.proxiedWorld : Lnet/minecraft/world/WorldServer;
    GETFIELD net/minecraft/world/WorldServer.field_73003_n : F
    PUTFIELD cofh/asmhooks/world/WorldServerProxy.field_73003_n : F
   L3
    LINENUMBER 46 L3
    ALOAD 0
    ALOAD 0
    GETFIELD cofh/asmhooks/world/WorldServerProxy.proxiedWorld : Lnet/minecraft/world/WorldServer;
    GETFIELD net/minecraft/world/WorldServer.field_73004_o : F
    PUTFIELD cofh/asmhooks/world/WorldServerProxy.field_73004_o : F
   L4
    LINENUMBER 47 L4
    ALOAD 0
    ALOAD 0
    GETFIELD cofh/asmhooks/world/WorldServerProxy.proxiedWorld : Lnet/minecraft/world/WorldServer;
    GETFIELD net/minecraft/world/WorldServer.field_73018_p : F
    PUTFIELD cofh/asmhooks/world/WorldServerProxy.field_73018_p : F
   L5
    LINENUMBER 48 L5
    ALOAD 0
    ALOAD 0
    GETFIELD cofh/asmhooks/world/WorldServerProxy.proxiedWorld : Lnet/minecraft/world/WorldServer;
    GETFIELD net/minecraft/world/WorldServer.field_73017_q : F
    PUTFIELD cofh/asmhooks/world/WorldServerProxy.field_73017_q : F
   L6
    LINENUMBER 49 L6
    ALOAD 0
    INVOKEVIRTUAL cofh/asmhooks/world/WorldServerProxy.func_72912_H ()Lnet/minecraft/world/storage/WorldInfo;
    ALOAD 0
    GETFIELD cofh/asmhooks/world/WorldServerProxy.proxiedWorld : Lnet/minecraft/world/WorldServer;
    INVOKEVIRTUAL net/minecraft/world/WorldServer.func_175659_aa ()Lnet/minecraft/world/EnumDifficulty;
    INVOKEVIRTUAL net/minecraft/world/storage/WorldInfo.func_176144_a (Lnet/minecraft/world/EnumDifficulty;)V
   L7
    LINENUMBER 50 L7
    ALOAD 0
    ALOAD 0
    GETFIELD cofh/asmhooks/world/WorldServerProxy.proxiedWorld : Lnet/minecraft/world/WorldServer;
    GETFIELD net/minecraft/world/WorldServer.field_73016_r : I
    PUTFIELD cofh/asmhooks/world/WorldServerProxy.field_73016_r : I
   L8
    LINENUMBER 51 L8
    ALOAD 0
    ALOAD 0
    GETFIELD cofh/asmhooks/world/WorldServerProxy.proxiedWorld : Lnet/minecraft/world/WorldServer;
    GETFIELD net/minecraft/world/WorldServer.field_73068_P : Z
    PUTFIELD cofh/asmhooks/world/WorldServerProxy.field_73068_P : Z
   L9
    LINENUMBER 52 L9
    ALOAD 0
    ALOAD 0
    GETFIELD cofh/asmhooks/world/WorldServerProxy.proxiedWorld : Lnet/minecraft/world/WorldServer;
    INVOKEVIRTUAL net/minecraft/world/WorldServer.func_72863_F ()Lnet/minecraft/world/gen/ChunkProviderServer;
    PUTFIELD cofh/asmhooks/world/WorldServerProxy.field_73020_y : Lnet/minecraft/world/chunk/IChunkProvider;
   L10
    LINENUMBER 53 L10
    ALOAD 0
    ALOAD 0
    GETFIELD cofh/asmhooks/world/WorldServerProxy.proxiedWorld : Lnet/minecraft/world/WorldServer;
    GETFIELD net/minecraft/world/WorldServer.field_73058_d : Z
    PUTFIELD cofh/asmhooks/world/WorldServerProxy.field_73058_d : Z
   L11
    LINENUMBER 54 L11
    ALOAD 0
    ALOAD 0
    GETFIELD cofh/asmhooks/world/WorldServerProxy.proxiedWorld : Lnet/minecraft/world/WorldServer;
    GETFIELD net/minecraft/world/WorldServer.captureBlockSnapshots : Z
    PUTFIELD cofh/asmhooks/world/WorldServerProxy.captureBlockSnapshots : Z
   L12
    LINENUMBER 55 L12
    ALOAD 0
    ALOAD 0
    GETFIELD cofh/asmhooks/world/WorldServerProxy.proxiedWorld : Lnet/minecraft/world/WorldServer;
    GETFIELD net/minecraft/world/WorldServer.restoringBlockSnapshots : Z
    PUTFIELD cofh/asmhooks/world/WorldServerProxy.restoringBlockSnapshots : Z
   L13
    LINENUMBER 56 L13
    ALOAD 0
    ALOAD 0
    GETFIELD cofh/asmhooks/world/WorldServerProxy.proxiedWorld : Lnet/minecraft/world/WorldServer;
    GETFIELD net/minecraft/world/WorldServer.field_72982_D : Lnet/minecraft/village/VillageCollection;
    PUTFIELD cofh/asmhooks/world/WorldServerProxy.field_72982_D : Lnet/minecraft/village/VillageCollection;
   L14
    LINENUMBER 57 L14
    ALOAD 0
    ALOAD 0
    GETFIELD cofh/asmhooks/world/WorldServerProxy.proxiedWorld : Lnet/minecraft/world/WorldServer;
    GETFIELD net/minecraft/world/WorldServer.customTeleporters : Ljava/util/List;
    PUTFIELD cofh/asmhooks/world/WorldServerProxy.customTeleporters : Ljava/util/List;
   L15
    LINENUMBER 58 L15
    RETURN
   L16
    LOCALVARIABLE this Lcofh/asmhooks/world/WorldServerProxy; L0 L16 0
    MAXSTACK = 2
    MAXLOCALS = 1

  // access flags 0x1001
  public synthetic func_191504_a(Lnet/minecraft/entity/Entity;Lnet/minecraft/util/math/AxisAlignedBB;ZLjava/util/List;)Z
    ALOAD 0
    GETFIELD cofh/asmhooks/world/WorldServerProxy.proxiedWorld : Lnet/minecraft/world/WorldServer;
    ALOAD 1
    ALOAD 2
    ILOAD 3
    ALOAD 4
    INVOKEVIRTUAL net/minecraft/world/World.func_191504_a (Lnet/minecraft/entity/Entity;Lnet/minecraft/util/math/AxisAlignedBB;ZLjava/util/List;)Z
    IRETURN
    MAXSTACK = 5
    MAXLOCALS = 5

  // access flags 0x1001
  public synthetic func_72954_a(Lnet/minecraft/world/IWorldEventListener;)V
    ALOAD 0
    GETFIELD cofh/asmhooks/world/WorldServerProxy.proxiedWorld : Lnet/minecraft/world/WorldServer;
    ALOAD 1
    INVOKEVIRTUAL net/minecraft/world/World.func_72954_a (Lnet/minecraft/world/IWorldEventListener;)V
    RETURN
    MAXSTACK = 2
    MAXLOCALS = 2

  // access flags 0x1001
  public synthetic func_175651_c(Lnet/minecraft/util/math/BlockPos;Lnet/minecraft/util/EnumFacing;)I
    ALOAD 0
    GETFIELD cofh/asmhooks/world/WorldServerProxy.proxiedWorld : Lnet/minecraft/world/WorldServer;
    ALOAD 1
    ALOAD 2
    INVOKEVIRTUAL net/minecraft/world/World.func_175651_c (Lnet/minecraft/util/math/BlockPos;Lnet/minecraft/util/EnumFacing;)I
    IRETURN
    MAXSTACK = 3
    MAXLOCALS = 3

  // access flags 0x1001
  public synthetic func_175627_a(Lnet/minecraft/util/math/BlockPos;Lnet/minecraft/util/EnumFacing;)I
    ALOAD 0
    GETFIELD cofh/asmhooks/world/WorldServerProxy.proxiedWorld : Lnet/minecraft/world/WorldServer;
    ALOAD 1
    ALOAD 2
    INVOKEVIRTUAL net/minecraft/world/World.func_175627_a (Lnet/minecraft/util/math/BlockPos;Lnet/minecraft/util/EnumFacing;)I
    IRETURN
    MAXSTACK = 3
    MAXLOCALS = 3

  // access flags 0x1001
  public synthetic func_175727_C(Lnet/minecraft/util/math/BlockPos;)Z
    ALOAD 0
    GETFIELD cofh/asmhooks/world/WorldServerProxy.proxiedWorld : Lnet/minecraft/world/WorldServer;
    ALOAD 1
    INVOKEVIRTUAL net/minecraft/world/World.func_175727_C (Lnet/minecraft/util/math/BlockPos;)Z
    IRETURN
    MAXSTACK = 2
    MAXLOCALS = 2

  // access flags 0x1001
  public synthetic func_72912_H()Lnet/minecraft/world/storage/WorldInfo;
    ALOAD 0
    GETFIELD cofh/asmhooks/world/WorldServerProxy.proxiedWorld : Lnet/minecraft/world/WorldServer;
    INVOKEVIRTUAL net/minecraft/world/World.func_72912_H ()Lnet/minecraft/world/storage/WorldInfo;
    ARETURN
    MAXSTACK = 1
    MAXLOCALS = 1

  // access flags 0x1001
  public synthetic func_175694_M()Lnet/minecraft/util/math/BlockPos;
    ALOAD 0
    GETFIELD cofh/asmhooks/world/WorldServerProxy.proxiedWorld : Lnet/minecraft/world/WorldServer;
    INVOKEVIRTUAL net/minecraft/world/World.func_175694_M ()Lnet/minecraft/util/math/BlockPos;
    ARETURN
    MAXSTACK = 1
    MAXLOCALS = 1

  // access flags 0x1001
  public synthetic func_180494_b(Lnet/minecraft/util/math/BlockPos;)Lnet/minecraft/world/biome/Biome;
    ALOAD 0
    GETFIELD cofh/asmhooks/world/WorldServerProxy.proxiedWorld : Lnet/minecraft/world/WorldServer;
    ALOAD 1
    INVOKEVIRTUAL net/minecraft/world/World.func_180494_b (Lnet/minecraft/util/math/BlockPos;)Lnet/minecraft/world/biome/Biome;
    ARETURN
    MAXSTACK = 2
    MAXLOCALS = 2

  // access flags 0x1001
  public synthetic getBiomeForCoordsBody(Lnet/minecraft/util/math/BlockPos;)Lnet/minecraft/world/biome/Biome;
    ALOAD 0
    GETFIELD cofh/asmhooks/world/WorldServerProxy.proxiedWorld : Lnet/minecraft/world/WorldServer;
    ALOAD 1
    INVOKEVIRTUAL net/minecraft/world/World.getBiomeForCoordsBody (Lnet/minecraft/util/math/BlockPos;)Lnet/minecraft/world/biome/Biome;
    ARETURN
    MAXSTACK = 2
    MAXLOCALS = 2

  // access flags 0x1001
  public synthetic func_175667_e(Lnet/minecraft/util/math/BlockPos;)Z
    ALOAD 0
    GETFIELD cofh/asmhooks/world/WorldServerProxy.proxiedWorld : Lnet/minecraft/world/WorldServer;
    ALOAD 1
    INVOKEVIRTUAL net/minecraft/world/World.func_175667_e (Lnet/minecraft/util/math/BlockPos;)Z
    IRETURN
    MAXSTACK = 2
    MAXLOCALS = 2

  // access flags 0x1001
  public synthetic func_175726_f(Lnet/minecraft/util/math/BlockPos;)Lnet/minecraft/world/chunk/Chunk;
    ALOAD 0
    GETFIELD cofh/asmhooks/world/WorldServerProxy.proxiedWorld : Lnet/minecraft/world/WorldServer;
    ALOAD 1
    INVOKEVIRTUAL net/minecraft/world/World.func_175726_f (Lnet/minecraft/util/math/BlockPos;)Lnet/minecraft/world/chunk/Chunk;
    ARETURN
    MAXSTACK = 2
    MAXLOCALS = 2

  // access flags 0x1001
  public synthetic func_72959_q()Lnet/minecraft/world/biome/BiomeProvider;
    ALOAD 0
    GETFIELD cofh/asmhooks/world/WorldServerProxy.proxiedWorld : Lnet/minecraft/world/WorldServer;
    INVOKEVIRTUAL net/minecraft/world/World.func_72959_q ()Lnet/minecraft/world/biome/BiomeProvider;
    ARETURN
    MAXSTACK = 1
    MAXLOCALS = 1

  // access flags 0x1001
  public synthetic func_184141_c(Lnet/minecraft/util/math/BlockPos;)Lnet/minecraft/block/state/IBlockState;
    ALOAD 0
    GETFIELD cofh/asmhooks/world/WorldServerProxy.proxiedWorld : Lnet/minecraft/world/WorldServer;
    ALOAD 1
    INVOKEVIRTUAL net/minecraft/world/World.func_184141_c (Lnet/minecraft/util/math/BlockPos;)Lnet/minecraft/block/state/IBlockState;
    ARETURN
    MAXSTACK = 2
    MAXLOCALS = 2

  // access flags 0x1001
  public synthetic func_181545_F()I
    ALOAD 0
    GETFIELD cofh/asmhooks/world/WorldServerProxy.proxiedWorld : Lnet/minecraft/world/WorldServer;
    INVOKEVIRTUAL net/minecraft/world/World.func_181545_F ()I
    IRETURN
    MAXSTACK = 1
    MAXLOCALS = 1

  // access flags 0x1001
  public synthetic func_175623_d(Lnet/minecraft/util/math/BlockPos;)Z
    ALOAD 0
    GETFIELD cofh/asmhooks/world/WorldServerProxy.proxiedWorld : Lnet/minecraft/world/WorldServer;
    ALOAD 1
    INVOKEVIRTUAL net/minecraft/world/World.func_175623_d (Lnet/minecraft/util/math/BlockPos;)Z
    IRETURN
    MAXSTACK = 2
    MAXLOCALS = 2

  // access flags 0x1001
  public synthetic func_180495_p(Lnet/minecraft/util/math/BlockPos;)Lnet/minecraft/block/state/IBlockState;
    ALOAD 0
    GETFIELD cofh/asmhooks/world/WorldServerProxy.proxiedWorld : Lnet/minecraft/world/WorldServer;
    ALOAD 1
    INVOKEVIRTUAL net/minecraft/world/World.func_180495_p (Lnet/minecraft/util/math/BlockPos;)Lnet/minecraft/block/state/IBlockState;
    ARETURN
    MAXSTACK = 2
    MAXLOCALS = 2

  // access flags 0x1001
  public synthetic func_175701_a(Lnet/minecraft/util/math/BlockPos;)Z
    ALOAD 0
    GETFIELD cofh/asmhooks/world/WorldServerProxy.proxiedWorld : Lnet/minecraft/world/WorldServer;
    ALOAD 1
    INVOKEVIRTUAL net/minecraft/world/World.func_175701_a (Lnet/minecraft/util/math/BlockPos;)Z
    IRETURN
    MAXSTACK = 2
    MAXLOCALS = 2

  // access flags 0x1001
  public synthetic func_189509_E(Lnet/minecraft/util/math/BlockPos;)Z
    ALOAD 0
    GETFIELD cofh/asmhooks/world/WorldServerProxy.proxiedWorld : Lnet/minecraft/world/WorldServer;
    ALOAD 1
    INVOKEVIRTUAL net/minecraft/world/World.func_189509_E (Lnet/minecraft/util/math/BlockPos;)Z
    IRETURN
    MAXSTACK = 2
    MAXLOCALS = 2

  // access flags 0x1001
  public synthetic func_175668_a(Lnet/minecraft/util/math/BlockPos;Z)Z
    ALOAD 0
    GETFIELD cofh/asmhooks/world/WorldServerProxy.proxiedWorld : Lnet/minecraft/world/WorldServer;
    ALOAD 1
    ILOAD 2
    INVOKEVIRTUAL net/minecraft/world/World.func_175668_a (Lnet/minecraft/util/math/BlockPos;Z)Z
    IRETURN
    MAXSTACK = 3
    MAXLOCALS = 3

  // access flags 0x1001
  public synthetic func_175697_a(Lnet/minecraft/util/math/BlockPos;I)Z
    ALOAD 0
    GETFIELD cofh/asmhooks/world/WorldServerProxy.proxiedWorld : Lnet/minecraft/world/WorldServer;
    ALOAD 1
    ILOAD 2
    INVOKEVIRTUAL net/minecraft/world/World.func_175697_a (Lnet/minecraft/util/math/BlockPos;I)Z
    IRETURN
    MAXSTACK = 3
    MAXLOCALS = 3

  // access flags 0x1001
  public synthetic func_175648_a(Lnet/minecraft/util/math/BlockPos;IZ)Z
    ALOAD 0
    GETFIELD cofh/asmhooks/world/WorldServerProxy.proxiedWorld : Lnet/minecraft/world/WorldServer;
    ALOAD 1
    ILOAD 2
    ILOAD 3
    INVOKEVIRTUAL net/minecraft/world/World.func_175648_a (Lnet/minecraft/util/math/BlockPos;IZ)Z
    IRETURN
    MAXSTACK = 4
    MAXLOCALS = 4

  // access flags 0x1001
  public synthetic func_175663_a(IIIIIIZ)Z
    ALOAD 0
    GETFIELD cofh/asmhooks/world/WorldServerProxy.proxiedWorld : Lnet/minecraft/world/WorldServer;
    ILOAD 1
    ILOAD 2
    ILOAD 3
    ILOAD 4
    ILOAD 5
    ILOAD 6
    ILOAD 7
    INVOKEVIRTUAL net/minecraft/world/World.func_175663_a (IIIIIIZ)Z
    IRETURN
    MAXSTACK = 8
    MAXLOCALS = 8

  // access flags 0x1001
  public synthetic func_175707_a(Lnet/minecraft/util/math/BlockPos;Lnet/minecraft/util/math/BlockPos;)Z
    ALOAD 0
    GETFIELD cofh/asmhooks/world/WorldServerProxy.proxiedWorld : Lnet/minecraft/world/WorldServer;
    ALOAD 1
    ALOAD 2
    INVOKEVIRTUAL net/minecraft/world/World.func_175707_a (Lnet/minecraft/util/math/BlockPos;Lnet/minecraft/util/math/BlockPos;)Z
    IRETURN
    MAXSTACK = 3
    MAXLOCALS = 3

  // access flags 0x1001
  public synthetic func_175706_a(Lnet/minecraft/util/math/BlockPos;Lnet/minecraft/util/math/BlockPos;Z)Z
    ALOAD 0
    GETFIELD cofh/asmhooks/world/WorldServerProxy.proxiedWorld : Lnet/minecraft/world/WorldServer;
    ALOAD 1
    ALOAD 2
    ILOAD 3
    INVOKEVIRTUAL net/minecraft/world/World.func_175706_a (Lnet/minecraft/util/math/BlockPos;Lnet/minecraft/util/math/BlockPos;Z)Z
    IRETURN
    MAXSTACK = 4
    MAXLOCALS = 4

  // access flags 0x1001
  public synthetic func_175711_a(Lnet/minecraft/world/gen/structure/StructureBoundingBox;)Z
    ALOAD 0
    GETFIELD cofh/asmhooks/world/WorldServerProxy.proxiedWorld : Lnet/minecraft/world/WorldServer;
    ALOAD 1
    INVOKEVIRTUAL net/minecraft/world/World.func_175711_a (Lnet/minecraft/world/gen/structure/StructureBoundingBox;)Z
    IRETURN
    MAXSTACK = 2
    MAXLOCALS = 2

  // access flags 0x1001
  public synthetic func_175639_b(Lnet/minecraft/world/gen/structure/StructureBoundingBox;Z)Z
    ALOAD 0
    GETFIELD cofh/asmhooks/world/WorldServerProxy.proxiedWorld : Lnet/minecraft/world/WorldServer;
    ALOAD 1
    ILOAD 2
    INVOKEVIRTUAL net/minecraft/world/World.func_175639_b (Lnet/minecraft/world/gen/structure/StructureBoundingBox;Z)Z
    IRETURN
    MAXSTACK = 3
    MAXLOCALS = 3

  // access flags 0x1001
  public synthetic markAndNotifyBlock(Lnet/minecraft/util/math/BlockPos;Lnet/minecraft/world/chunk/Chunk;Lnet/minecraft/block/state/IBlockState;Lnet/minecraft/block/state/IBlockState;I)V
    ALOAD 0
    GETFIELD cofh/asmhooks/world/WorldServerProxy.proxiedWorld : Lnet/minecraft/world/WorldServer;
    ALOAD 1
    ALOAD 2
    ALOAD 3
    ALOAD 4
    ILOAD 5
    INVOKEVIRTUAL net/minecraft/world/World.markAndNotifyBlock (Lnet/minecraft/util/math/BlockPos;Lnet/minecraft/world/chunk/Chunk;Lnet/minecraft/block/state/IBlockState;Lnet/minecraft/block/state/IBlockState;I)V
    RETURN
    MAXSTACK = 6
    MAXLOCALS = 6

  // access flags 0x1001
  public synthetic func_72964_e(II)Lnet/minecraft/world/chunk/Chunk;
    ALOAD 0
    GETFIELD cofh/asmhooks/world/WorldServerProxy.proxiedWorld : Lnet/minecraft/world/WorldServer;
    ILOAD 1
    ILOAD 2
    INVOKEVIRTUAL net/minecraft/world/World.func_72964_e (II)Lnet/minecraft/world/chunk/Chunk;
    ARETURN
    MAXSTACK = 3
    MAXLOCALS = 3

  // access flags 0x1001
  public synthetic func_180501_a(Lnet/minecraft/util/math/BlockPos;Lnet/minecraft/block/state/IBlockState;I)Z
    ALOAD 0
    GETFIELD cofh/asmhooks/world/WorldServerProxy.proxiedWorld : Lnet/minecraft/world/WorldServer;
    ALOAD 1
    ALOAD 2
    ILOAD 3
    INVOKEVIRTUAL net/minecraft/world/World.func_180501_a (Lnet/minecraft/util/math/BlockPos;Lnet/minecraft/block/state/IBlockState;I)Z
    IRETURN
    MAXSTACK = 4
    MAXLOCALS = 4

  // access flags 0x1001
  public synthetic func_175664_x(Lnet/minecraft/util/math/BlockPos;)Z
    ALOAD 0
    GETFIELD cofh/asmhooks/world/WorldServerProxy.proxiedWorld : Lnet/minecraft/world/WorldServer;
    ALOAD 1
    INVOKEVIRTUAL net/minecraft/world/World.func_175664_x (Lnet/minecraft/util/math/BlockPos;)Z
    IRETURN
    MAXSTACK = 2
    MAXLOCALS = 2

  // access flags 0x1001
  public synthetic func_184138_a(Lnet/minecraft/util/math/BlockPos;Lnet/minecraft/block/state/IBlockState;Lnet/minecraft/block/state/IBlockState;I)V
    ALOAD 0
    GETFIELD cofh/asmhooks/world/WorldServerProxy.proxiedWorld : Lnet/minecraft/world/WorldServer;
    ALOAD 1
    ALOAD 2
    ALOAD 3
    ILOAD 4
    INVOKEVIRTUAL net/minecraft/world/World.func_184138_a (Lnet/minecraft/util/math/BlockPos;Lnet/minecraft/block/state/IBlockState;Lnet/minecraft/block/state/IBlockState;I)V
    RETURN
    MAXSTACK = 5
    MAXLOCALS = 5

  // access flags 0x1001
  public synthetic func_175722_b(Lnet/minecraft/util/math/BlockPos;Lnet/minecraft/block/Block;)V
    ALOAD 0
    GETFIELD cofh/asmhooks/world/WorldServerProxy.proxiedWorld : Lnet/minecraft/world/WorldServer;
    ALOAD 1
    ALOAD 2
    INVOKEVIRTUAL net/minecraft/world/World.func_175722_b (Lnet/minecraft/util/math/BlockPos;Lnet/minecraft/block/Block;)V
    RETURN
    MAXSTACK = 3
    MAXLOCALS = 3

  // access flags 0x1001
  public synthetic func_175666_e(Lnet/minecraft/util/math/BlockPos;Lnet/minecraft/block/Block;)V
    ALOAD 0
    GETFIELD cofh/asmhooks/world/WorldServerProxy.proxiedWorld : Lnet/minecraft/world/WorldServer;
    ALOAD 1
    ALOAD 2
    INVOKEVIRTUAL net/minecraft/world/World.func_175666_e (Lnet/minecraft/util/math/BlockPos;Lnet/minecraft/block/Block;)V
    RETURN
    MAXSTACK = 3
    MAXLOCALS = 3

  // access flags 0x1001
  public synthetic func_175698_g(Lnet/minecraft/util/math/BlockPos;)Z
    ALOAD 0
    GETFIELD cofh/asmhooks/world/WorldServerProxy.proxiedWorld : Lnet/minecraft/world/WorldServer;
    ALOAD 1
    INVOKEVIRTUAL net/minecraft/world/World.func_175698_g (Lnet/minecraft/util/math/BlockPos;)Z
    IRETURN
    MAXSTACK = 2
    MAXLOCALS = 2

  // access flags 0x1001
  public synthetic func_175655_b(Lnet/minecraft/util/math/BlockPos;Z)Z
    ALOAD 0
    GETFIELD cofh/asmhooks/world/WorldServerProxy.proxiedWorld : Lnet/minecraft/world/WorldServer;
    ALOAD 1
    ILOAD 2
    INVOKEVIRTUAL net/minecraft/world/World.func_175655_b (Lnet/minecraft/util/math/BlockPos;Z)Z
    IRETURN
    MAXSTACK = 3
    MAXLOCALS = 3

  // access flags 0x1001
  public synthetic func_175718_b(ILnet/minecraft/util/math/BlockPos;I)V
    ALOAD 0
    GETFIELD cofh/asmhooks/world/WorldServerProxy.proxiedWorld : Lnet/minecraft/world/WorldServer;
    ILOAD 1
    ALOAD 2
    ILOAD 3
    INVOKEVIRTUAL net/minecraft/world/World.func_175718_b (ILnet/minecraft/util/math/BlockPos;I)V
    RETURN
    MAXSTACK = 4
    MAXLOCALS = 4

  // access flags 0x1001
  public synthetic func_175656_a(Lnet/minecraft/util/math/BlockPos;Lnet/minecraft/block/state/IBlockState;)Z
    ALOAD 0
    GETFIELD cofh/asmhooks/world/WorldServerProxy.proxiedWorld : Lnet/minecraft/world/WorldServer;
    ALOAD 1
    ALOAD 2
    INVOKEVIRTUAL net/minecraft/world/World.func_175656_a (Lnet/minecraft/util/math/BlockPos;Lnet/minecraft/block/state/IBlockState;)Z
    IRETURN
    MAXSTACK = 3
    MAXLOCALS = 3

  // access flags 0x1001
  public synthetic func_175685_c(Lnet/minecraft/util/math/BlockPos;Lnet/minecraft/block/Block;)V
    ALOAD 0
    GETFIELD cofh/asmhooks/world/WorldServerProxy.proxiedWorld : Lnet/minecraft/world/WorldServer;
    ALOAD 1
    ALOAD 2
    INVOKEVIRTUAL net/minecraft/world/World.func_175685_c (Lnet/minecraft/util/math/BlockPos;Lnet/minecraft/block/Block;)V
    RETURN
    MAXSTACK = 3
    MAXLOCALS = 3

  // access flags 0x1001
  public synthetic func_72975_g(IIII)V
    ALOAD 0
    GETFIELD cofh/asmhooks/world/WorldServerProxy.proxiedWorld : Lnet/minecraft/world/WorldServer;
    ILOAD 1
    ILOAD 2
    ILOAD 3
    ILOAD 4
    INVOKEVIRTUAL net/minecraft/world/World.func_72975_g (IIII)V
    RETURN
    MAXSTACK = 5
    MAXLOCALS = 5

  // access flags 0x1001
  public synthetic func_180500_c(Lnet/minecraft/world/EnumSkyBlock;Lnet/minecraft/util/math/BlockPos;)Z
    ALOAD 0
    GETFIELD cofh/asmhooks/world/WorldServerProxy.proxiedWorld : Lnet/minecraft/world/WorldServer;
    ALOAD 1
    ALOAD 2
    INVOKEVIRTUAL net/minecraft/world/World.func_180500_c (Lnet/minecraft/world/EnumSkyBlock;Lnet/minecraft/util/math/BlockPos;)Z
    IRETURN
    MAXSTACK = 3
    MAXLOCALS = 3

  // access flags 0x1001
  public synthetic func_147458_c(IIIIII)V
    ALOAD 0
    GETFIELD cofh/asmhooks/world/WorldServerProxy.proxiedWorld : Lnet/minecraft/world/WorldServer;
    ILOAD 1
    ILOAD 2
    ILOAD 3
    ILOAD 4
    ILOAD 5
    ILOAD 6
    INVOKEVIRTUAL net/minecraft/world/World.func_147458_c (IIIIII)V
    RETURN
    MAXSTACK = 7
    MAXLOCALS = 7

  // access flags 0x1001
  public synthetic func_175704_b(Lnet/minecraft/util/math/BlockPos;Lnet/minecraft/util/math/BlockPos;)V
    ALOAD 0
    GETFIELD cofh/asmhooks/world/WorldServerProxy.proxiedWorld : Lnet/minecraft/world/WorldServer;
    ALOAD 1
    ALOAD 2
    INVOKEVIRTUAL net/minecraft/world/World.func_175704_b (Lnet/minecraft/util/math/BlockPos;Lnet/minecraft/util/math/BlockPos;)V
    RETURN
    MAXSTACK = 3
    MAXLOCALS = 3

  // access flags 0x1001
  public synthetic func_180496_d(Lnet/minecraft/util/math/BlockPos;Lnet/minecraft/block/Block;)V
    ALOAD 0
    GETFIELD cofh/asmhooks/world/WorldServerProxy.proxiedWorld : Lnet/minecraft/world/WorldServer;
    ALOAD 1
    ALOAD 2
    INVOKEVIRTUAL net/minecraft/world/World.func_180496_d (Lnet/minecraft/util/math/BlockPos;Lnet/minecraft/block/Block;)V
    RETURN
    MAXSTACK = 3
    MAXLOCALS = 3

  // access flags 0x1001
  public synthetic func_175695_a(Lnet/minecraft/util/math/BlockPos;Lnet/minecraft/block/Block;Lnet/minecraft/util/EnumFacing;)V
    ALOAD 0
    GETFIELD cofh/asmhooks/world/WorldServerProxy.proxiedWorld : Lnet/minecraft/world/WorldServer;
    ALOAD 1
    ALOAD 2
    ALOAD 3
    INVOKEVIRTUAL net/minecraft/world/World.func_175695_a (Lnet/minecraft/util/math/BlockPos;Lnet/minecraft/block/Block;Lnet/minecraft/util/EnumFacing;)V
    RETURN
    MAXSTACK = 4
    MAXLOCALS = 4

  // access flags 0x1001
  public synthetic func_175678_i(Lnet/minecraft/util/math/BlockPos;)Z
    ALOAD 0
    GETFIELD cofh/asmhooks/world/WorldServerProxy.proxiedWorld : Lnet/minecraft/world/WorldServer;
    ALOAD 1
    INVOKEVIRTUAL net/minecraft/world/World.func_175678_i (Lnet/minecraft/util/math/BlockPos;)Z
    IRETURN
    MAXSTACK = 2
    MAXLOCALS = 2

  // access flags 0x1001
  public synthetic func_175710_j(Lnet/minecraft/util/math/BlockPos;)Z
    ALOAD 0
    GETFIELD cofh/asmhooks/world/WorldServerProxy.proxiedWorld : Lnet/minecraft/world/WorldServer;
    ALOAD 1
    INVOKEVIRTUAL net/minecraft/world/World.func_175710_j (Lnet/minecraft/util/math/BlockPos;)Z
    IRETURN
    MAXSTACK = 2
    MAXLOCALS = 2

  // access flags 0x1001
  public synthetic func_175699_k(Lnet/minecraft/util/math/BlockPos;)I
    ALOAD 0
    GETFIELD cofh/asmhooks/world/WorldServerProxy.proxiedWorld : Lnet/minecraft/world/WorldServer;
    ALOAD 1
    INVOKEVIRTUAL net/minecraft/world/World.func_175699_k (Lnet/minecraft/util/math/BlockPos;)I
    IRETURN
    MAXSTACK = 2
    MAXLOCALS = 2

  // access flags 0x1001
  public synthetic func_175671_l(Lnet/minecraft/util/math/BlockPos;)I
    ALOAD 0
    GETFIELD cofh/asmhooks/world/WorldServerProxy.proxiedWorld : Lnet/minecraft/world/WorldServer;
    ALOAD 1
    INVOKEVIRTUAL net/minecraft/world/World.func_175671_l (Lnet/minecraft/util/math/BlockPos;)I
    IRETURN
    MAXSTACK = 2
    MAXLOCALS = 2

  // access flags 0x1001
  public synthetic func_175721_c(Lnet/minecraft/util/math/BlockPos;Z)I
    ALOAD 0
    GETFIELD cofh/asmhooks/world/WorldServerProxy.proxiedWorld : Lnet/minecraft/world/WorldServer;
    ALOAD 1
    ILOAD 2
    INVOKEVIRTUAL net/minecraft/world/World.func_175721_c (Lnet/minecraft/util/math/BlockPos;Z)I
    IRETURN
    MAXSTACK = 3
    MAXLOCALS = 3

  // access flags 0x1001
  public synthetic func_175645_m(Lnet/minecraft/util/math/BlockPos;)Lnet/minecraft/util/math/BlockPos;
    ALOAD 0
    GETFIELD cofh/asmhooks/world/WorldServerProxy.proxiedWorld : Lnet/minecraft/world/WorldServer;
    ALOAD 1
    INVOKEVIRTUAL net/minecraft/world/World.func_175645_m (Lnet/minecraft/util/math/BlockPos;)Lnet/minecraft/util/math/BlockPos;
    ARETURN
    MAXSTACK = 2
    MAXLOCALS = 2

  // access flags 0x1001
  public synthetic func_189649_b(II)I
    ALOAD 0
    GETFIELD cofh/asmhooks/world/WorldServerProxy.proxiedWorld : Lnet/minecraft/world/WorldServer;
    ILOAD 1
    ILOAD 2
    INVOKEVIRTUAL net/minecraft/world/World.func_189649_b (II)I
    IRETURN
    MAXSTACK = 3
    MAXLOCALS = 3

  // access flags 0x1001
  public synthetic func_82734_g(II)I
    ALOAD 0
    GETFIELD cofh/asmhooks/world/WorldServerProxy.proxiedWorld : Lnet/minecraft/world/WorldServer;
    ILOAD 1
    ILOAD 2
    INVOKEVIRTUAL net/minecraft/world/World.func_82734_g (II)I
    IRETURN
    MAXSTACK = 3
    MAXLOCALS = 3

  // access flags 0x1001
  public synthetic func_175642_b(Lnet/minecraft/world/EnumSkyBlock;Lnet/minecraft/util/math/BlockPos;)I
    ALOAD 0
    GETFIELD cofh/asmhooks/world/WorldServerProxy.proxiedWorld : Lnet/minecraft/world/WorldServer;
    ALOAD 1
    ALOAD 2
    INVOKEVIRTUAL net/minecraft/world/World.func_175642_b (Lnet/minecraft/world/EnumSkyBlock;Lnet/minecraft/util/math/BlockPos;)I
    IRETURN
    MAXSTACK = 3
    MAXLOCALS = 3

  // access flags 0x1001
  public synthetic func_175653_a(Lnet/minecraft/world/EnumSkyBlock;Lnet/minecraft/util/math/BlockPos;I)V
    ALOAD 0
    GETFIELD cofh/asmhooks/world/WorldServerProxy.proxiedWorld : Lnet/minecraft/world/WorldServer;
    ALOAD 1
    ALOAD 2
    ILOAD 3
    INVOKEVIRTUAL net/minecraft/world/World.func_175653_a (Lnet/minecraft/world/EnumSkyBlock;Lnet/minecraft/util/math/BlockPos;I)V
    RETURN
    MAXSTACK = 4
    MAXLOCALS = 4

  // access flags 0x1001
  public synthetic func_175679_n(Lnet/minecraft/util/math/BlockPos;)V
    ALOAD 0
    GETFIELD cofh/asmhooks/world/WorldServerProxy.proxiedWorld : Lnet/minecraft/world/WorldServer;
    ALOAD 1
    INVOKEVIRTUAL net/minecraft/world/World.func_175679_n (Lnet/minecraft/util/math/BlockPos;)V
    RETURN
    MAXSTACK = 2
    MAXLOCALS = 2

  // access flags 0x1001
  public synthetic func_175724_o(Lnet/minecraft/util/math/BlockPos;)F
    ALOAD 0
    GETFIELD cofh/asmhooks/world/WorldServerProxy.proxiedWorld : Lnet/minecraft/world/WorldServer;
    ALOAD 1
    INVOKEVIRTUAL net/minecraft/world/World.func_175724_o (Lnet/minecraft/util/math/BlockPos;)F
    FRETURN
    MAXSTACK = 2
    MAXLOCALS = 2

  // access flags 0x1001
  public synthetic func_72935_r()Z
    ALOAD 0
    GETFIELD cofh/asmhooks/world/WorldServerProxy.proxiedWorld : Lnet/minecraft/world/WorldServer;
    INVOKEVIRTUAL net/minecraft/world/World.func_72935_r ()Z
    IRETURN
    MAXSTACK = 1
    MAXLOCALS = 1

  // access flags 0x1001
  public synthetic func_72933_a(Lnet/minecraft/util/math/Vec3d;Lnet/minecraft/util/math/Vec3d;)Lnet/minecraft/util/math/RayTraceResult;
    ALOAD 0
    GETFIELD cofh/asmhooks/world/WorldServerProxy.proxiedWorld : Lnet/minecraft/world/WorldServer;
    ALOAD 1
    ALOAD 2
    INVOKEVIRTUAL net/minecraft/world/World.func_72933_a (Lnet/minecraft/util/math/Vec3d;Lnet/minecraft/util/math/Vec3d;)Lnet/minecraft/util/math/RayTraceResult;
    ARETURN
    MAXSTACK = 3
    MAXLOCALS = 3

  // access flags 0x1001
  public synthetic func_147447_a(Lnet/minecraft/util/math/Vec3d;Lnet/minecraft/util/math/Vec3d;ZZZ)Lnet/minecraft/util/math/RayTraceResult;
    ALOAD 0
    GETFIELD cofh/asmhooks/world/WorldServerProxy.proxiedWorld : Lnet/minecraft/world/WorldServer;
    ALOAD 1
    ALOAD 2
    ILOAD 3
    ILOAD 4
    ILOAD 5
    INVOKEVIRTUAL net/minecraft/world/World.func_147447_a (Lnet/minecraft/util/math/Vec3d;Lnet/minecraft/util/math/Vec3d;ZZZ)Lnet/minecraft/util/math/RayTraceResult;
    ARETURN
    MAXSTACK = 6
    MAXLOCALS = 6

  // access flags 0x1001
  public synthetic func_72901_a(Lnet/minecraft/util/math/Vec3d;Lnet/minecraft/util/math/Vec3d;Z)Lnet/minecraft/util/math/RayTraceResult;
    ALOAD 0
    GETFIELD cofh/asmhooks/world/WorldServerProxy.proxiedWorld : Lnet/minecraft/world/WorldServer;
    ALOAD 1
    ALOAD 2
    ILOAD 3
    INVOKEVIRTUAL net/minecraft/world/World.func_72901_a (Lnet/minecraft/util/math/Vec3d;Lnet/minecraft/util/math/Vec3d;Z)Lnet/minecraft/util/math/RayTraceResult;
    ARETURN
    MAXSTACK = 4
    MAXLOCALS = 4

  // access flags 0x1001
  public synthetic func_184133_a(Lnet/minecraft/entity/player/EntityPlayer;Lnet/minecraft/util/math/BlockPos;Lnet/minecraft/util/SoundEvent;Lnet/minecraft/util/SoundCategory;FF)V
    ALOAD 0
    GETFIELD cofh/asmhooks/world/WorldServerProxy.proxiedWorld : Lnet/minecraft/world/WorldServer;
    ALOAD 1
    ALOAD 2
    ALOAD 3
    ALOAD 4
    FLOAD 5
    FLOAD 6
    INVOKEVIRTUAL net/minecraft/world/World.func_184133_a (Lnet/minecraft/entity/player/EntityPlayer;Lnet/minecraft/util/math/BlockPos;Lnet/minecraft/util/SoundEvent;Lnet/minecraft/util/SoundCategory;FF)V
    RETURN
    MAXSTACK = 7
    MAXLOCALS = 7

  // access flags 0x1001
  public synthetic func_184148_a(Lnet/minecraft/entity/player/EntityPlayer;DDDLnet/minecraft/util/SoundEvent;Lnet/minecraft/util/SoundCategory;FF)V
    ALOAD 0
    GETFIELD cofh/asmhooks/world/WorldServerProxy.proxiedWorld : Lnet/minecraft/world/WorldServer;
    ALOAD 1
    DLOAD 2
    DLOAD 4
    DLOAD 6
    ALOAD 8
    ALOAD 9
    FLOAD 10
    FLOAD 11
    INVOKEVIRTUAL net/minecraft/world/World.func_184148_a (Lnet/minecraft/entity/player/EntityPlayer;DDDLnet/minecraft/util/SoundEvent;Lnet/minecraft/util/SoundCategory;FF)V
    RETURN
    MAXSTACK = 12
    MAXLOCALS = 12

  // access flags 0x1001
  public synthetic func_184134_a(DDDLnet/minecraft/util/SoundEvent;Lnet/minecraft/util/SoundCategory;FFZ)V
    ALOAD 0
    GETFIELD cofh/asmhooks/world/WorldServerProxy.proxiedWorld : Lnet/minecraft/world/WorldServer;
    DLOAD 1
    DLOAD 3
    DLOAD 5
    ALOAD 7
    ALOAD 8
    FLOAD 9
    FLOAD 10
    ILOAD 11
    INVOKEVIRTUAL net/minecraft/world/World.func_184134_a (DDDLnet/minecraft/util/SoundEvent;Lnet/minecraft/util/SoundCategory;FFZ)V
    RETURN
    MAXSTACK = 12
    MAXLOCALS = 12

  // access flags 0x1001
  public synthetic func_184149_a(Lnet/minecraft/util/math/BlockPos;Lnet/minecraft/util/SoundEvent;)V
    ALOAD 0
    GETFIELD cofh/asmhooks/world/WorldServerProxy.proxiedWorld : Lnet/minecraft/world/WorldServer;
    ALOAD 1
    ALOAD 2
    INVOKEVIRTUAL net/minecraft/world/World.func_184149_a (Lnet/minecraft/util/math/BlockPos;Lnet/minecraft/util/SoundEvent;)V
    RETURN
    MAXSTACK = 3
    MAXLOCALS = 3

  // access flags 0x1081
  public transient synthetic varargs func_175688_a(Lnet/minecraft/util/EnumParticleTypes;DDDDDD[I)V
    ALOAD 0
    GETFIELD cofh/asmhooks/world/WorldServerProxy.proxiedWorld : Lnet/minecraft/world/WorldServer;
    ALOAD 1
    DLOAD 2
    DLOAD 4
    DLOAD 6
    DLOAD 8
    DLOAD 10
    DLOAD 12
    ALOAD 14
    INVOKEVIRTUAL net/minecraft/world/World.func_175688_a (Lnet/minecraft/util/EnumParticleTypes;DDDDDD[I)V
    RETURN
    MAXSTACK = 15
    MAXLOCALS = 15

  // access flags 0x1081
  public transient synthetic varargs func_175720_a(IZDDDDDD[I)V
    ALOAD 0
    GETFIELD cofh/asmhooks/world/WorldServerProxy.proxiedWorld : Lnet/minecraft/world/WorldServer;
    ILOAD 1
    ILOAD 2
    DLOAD 3
    DLOAD 5
    DLOAD 7
    DLOAD 9
    DLOAD 11
    DLOAD 13
    ALOAD 15
    INVOKEVIRTUAL net/minecraft/world/World.func_175720_a (IZDDDDDD[I)V
    RETURN
    MAXSTACK = 16
    MAXLOCALS = 16

  // access flags 0x1001
  public synthetic func_82737_E()J
    ALOAD 0
    GETFIELD cofh/asmhooks/world/WorldServerProxy.proxiedWorld : Lnet/minecraft/world/WorldServer;
    INVOKEVIRTUAL net/minecraft/world/World.func_82737_E ()J
    LRETURN
    MAXSTACK = 2
    MAXLOCALS = 1

  // access flags 0x1001
  public synthetic func_72820_D()J
    ALOAD 0
    GETFIELD cofh/asmhooks/world/WorldServerProxy.proxiedWorld : Lnet/minecraft/world/WorldServer;
    INVOKEVIRTUAL net/minecraft/world/World.func_72820_D ()J
    LRETURN
    MAXSTACK = 2
    MAXLOCALS = 1

  // access flags 0x1001
  public synthetic func_82736_K()Lnet/minecraft/world/GameRules;
    ALOAD 0
    GETFIELD cofh/asmhooks/world/WorldServerProxy.proxiedWorld : Lnet/minecraft/world/WorldServer;
    INVOKEVIRTUAL net/minecraft/world/World.func_82736_K ()Lnet/minecraft/world/GameRules;
    ARETURN
    MAXSTACK = 1
    MAXLOCALS = 1

  // access flags 0x1001
  public synthetic func_72914_a(Lnet/minecraft/crash/CrashReport;)Lnet/minecraft/crash/CrashReportCategory;
    ALOAD 0
    GETFIELD cofh/asmhooks/world/WorldServerProxy.proxiedWorld : Lnet/minecraft/world/WorldServer;
    ALOAD 1
    INVOKEVIRTUAL net/minecraft/world/World.func_72914_a (Lnet/minecraft/crash/CrashReport;)Lnet/minecraft/crash/CrashReportCategory;
    ARETURN
    MAXSTACK = 2
    MAXLOCALS = 2

  // access flags 0x1001
  public synthetic func_72891_a(ZZ)V
    ALOAD 0
    GETFIELD cofh/asmhooks/world/WorldServerProxy.proxiedWorld : Lnet/minecraft/world/WorldServer;
    ILOAD 1
    ILOAD 2
    INVOKEVIRTUAL net/minecraft/world/World.func_72891_a (ZZ)V
    RETURN
    MAXSTACK = 3
    MAXLOCALS = 3

  // access flags 0x1001
  public synthetic func_175659_aa()Lnet/minecraft/world/EnumDifficulty;
    ALOAD 0
    GETFIELD cofh/asmhooks/world/WorldServerProxy.proxiedWorld : Lnet/minecraft/world/WorldServer;
    INVOKEVIRTUAL net/minecraft/world/World.func_175659_aa ()Lnet/minecraft/world/EnumDifficulty;
    ARETURN
    MAXSTACK = 1
    MAXLOCALS = 1

  // access flags 0x1001
  public synthetic func_72900_e(Lnet/minecraft/entity/Entity;)V
    ALOAD 0
    GETFIELD cofh/asmhooks/world/WorldServerProxy.proxiedWorld : Lnet/minecraft/world/WorldServer;
    ALOAD 1
    INVOKEVIRTUAL net/minecraft/world/World.func_72900_e (Lnet/minecraft/entity/Entity;)V
    RETURN
    MAXSTACK = 2
    MAXLOCALS = 2

  // access flags 0x1001
  public synthetic func_72973_f(Lnet/minecraft/entity/Entity;)V
    ALOAD 0
    GETFIELD cofh/asmhooks/world/WorldServerProxy.proxiedWorld : Lnet/minecraft/world/WorldServer;
    ALOAD 1
    INVOKEVIRTUAL net/minecraft/world/World.func_72973_f (Lnet/minecraft/entity/Entity;)V
    RETURN
    MAXSTACK = 2
    MAXLOCALS = 2

  // access flags 0x1001
  public synthetic func_184144_a(Lnet/minecraft/entity/Entity;Lnet/minecraft/util/math/AxisAlignedBB;)Ljava/util/List;
    ALOAD 0
    GETFIELD cofh/asmhooks/world/WorldServerProxy.proxiedWorld : Lnet/minecraft/world/WorldServer;
    ALOAD 1
    ALOAD 2
    INVOKEVIRTUAL net/minecraft/world/World.func_184144_a (Lnet/minecraft/entity/Entity;Lnet/minecraft/util/math/AxisAlignedBB;)Ljava/util/List;
    ARETURN
    MAXSTACK = 3
    MAXLOCALS = 3

  // access flags 0x1001
  public synthetic func_175723_af()Lnet/minecraft/world/border/WorldBorder;
    ALOAD 0
    GETFIELD cofh/asmhooks/world/WorldServerProxy.proxiedWorld : Lnet/minecraft/world/WorldServer;
    INVOKEVIRTUAL net/minecraft/world/World.func_175723_af ()Lnet/minecraft/world/border/WorldBorder;
    ARETURN
    MAXSTACK = 1
    MAXLOCALS = 1

  // access flags 0x1001
  public synthetic func_175673_a(Lnet/minecraft/world/border/WorldBorder;Lnet/minecraft/entity/Entity;)Z
    ALOAD 0
    GETFIELD cofh/asmhooks/world/WorldServerProxy.proxiedWorld : Lnet/minecraft/world/WorldServer;
    ALOAD 1
    ALOAD 2
    INVOKEVIRTUAL net/minecraft/world/World.func_175673_a (Lnet/minecraft/world/border/WorldBorder;Lnet/minecraft/entity/Entity;)Z
    IRETURN
    MAXSTACK = 3
    MAXLOCALS = 3

  // access flags 0x1001
  public synthetic func_72839_b(Lnet/minecraft/entity/Entity;Lnet/minecraft/util/math/AxisAlignedBB;)Ljava/util/List;
    ALOAD 0
    GETFIELD cofh/asmhooks/world/WorldServerProxy.proxiedWorld : Lnet/minecraft/world/WorldServer;
    ALOAD 1
    ALOAD 2
    INVOKEVIRTUAL net/minecraft/world/World.func_72839_b (Lnet/minecraft/entity/Entity;Lnet/minecraft/util/math/AxisAlignedBB;)Ljava/util/List;
    ARETURN
    MAXSTACK = 3
    MAXLOCALS = 3

  // access flags 0x1001
  public synthetic func_147461_a(Lnet/minecraft/util/math/AxisAlignedBB;)Ljava/util/List;
    ALOAD 0
    GETFIELD cofh/asmhooks/world/WorldServerProxy.proxiedWorld : Lnet/minecraft/world/WorldServer;
    ALOAD 1
    INVOKEVIRTUAL net/minecraft/world/World.func_147461_a (Lnet/minecraft/util/math/AxisAlignedBB;)Ljava/util/List;
    ARETURN
    MAXSTACK = 2
    MAXLOCALS = 2

  // access flags 0x1001
  public synthetic func_72848_b(Lnet/minecraft/world/IWorldEventListener;)V
    ALOAD 0
    GETFIELD cofh/asmhooks/world/WorldServerProxy.proxiedWorld : Lnet/minecraft/world/WorldServer;
    ALOAD 1
    INVOKEVIRTUAL net/minecraft/world/World.func_72848_b (Lnet/minecraft/world/IWorldEventListener;)V
    RETURN
    MAXSTACK = 2
    MAXLOCALS = 2

  // access flags 0x1001
  public synthetic func_184143_b(Lnet/minecraft/util/math/AxisAlignedBB;)Z
    ALOAD 0
    GETFIELD cofh/asmhooks/world/WorldServerProxy.proxiedWorld : Lnet/minecraft/world/WorldServer;
    ALOAD 1
    INVOKEVIRTUAL net/minecraft/world/World.func_184143_b (Lnet/minecraft/util/math/AxisAlignedBB;)Z
    IRETURN
    MAXSTACK = 2
    MAXLOCALS = 2

  // access flags 0x1001
  public synthetic func_72967_a(F)I
    ALOAD 0
    GETFIELD cofh/asmhooks/world/WorldServerProxy.proxiedWorld : Lnet/minecraft/world/WorldServer;
    FLOAD 1
    INVOKEVIRTUAL net/minecraft/world/World.func_72967_a (F)I
    IRETURN
    MAXSTACK = 2
    MAXLOCALS = 2

  // access flags 0x1001
  public synthetic getSunBrightnessFactor(F)F
    ALOAD 0
    GETFIELD cofh/asmhooks/world/WorldServerProxy.proxiedWorld : Lnet/minecraft/world/WorldServer;
    FLOAD 1
    INVOKEVIRTUAL net/minecraft/world/World.getSunBrightnessFactor (F)F
    FRETURN
    MAXSTACK = 2
    MAXLOCALS = 2

  // access flags 0x1001
  public synthetic func_72826_c(F)F
    ALOAD 0
    GETFIELD cofh/asmhooks/world/WorldServerProxy.proxiedWorld : Lnet/minecraft/world/WorldServer;
    FLOAD 1
    INVOKEVIRTUAL net/minecraft/world/World.func_72826_c (F)F
    FRETURN
    MAXSTACK = 2
    MAXLOCALS = 2

  // access flags 0x1001
  public synthetic func_72867_j(F)F
    ALOAD 0
    GETFIELD cofh/asmhooks/world/WorldServerProxy.proxiedWorld : Lnet/minecraft/world/WorldServer;
    FLOAD 1
    INVOKEVIRTUAL net/minecraft/world/World.func_72867_j (F)F
    FRETURN
    MAXSTACK = 2
    MAXLOCALS = 2

  // access flags 0x1001
  public synthetic func_72819_i(F)F
    ALOAD 0
    GETFIELD cofh/asmhooks/world/WorldServerProxy.proxiedWorld : Lnet/minecraft/world/WorldServer;
    FLOAD 1
    INVOKEVIRTUAL net/minecraft/world/World.func_72819_i (F)F
    FRETURN
    MAXSTACK = 2
    MAXLOCALS = 2

  // access flags 0x1001
  public synthetic func_130001_d()F
    ALOAD 0
    GETFIELD cofh/asmhooks/world/WorldServerProxy.proxiedWorld : Lnet/minecraft/world/WorldServer;
    INVOKEVIRTUAL net/minecraft/world/World.func_130001_d ()F
    FRETURN
    MAXSTACK = 1
    MAXLOCALS = 1

  // access flags 0x1001
  public synthetic getCurrentMoonPhaseFactorBody()F
    ALOAD 0
    GETFIELD cofh/asmhooks/world/WorldServerProxy.proxiedWorld : Lnet/minecraft/world/WorldServer;
    INVOKEVIRTUAL net/minecraft/world/World.getCurrentMoonPhaseFactorBody ()F
    FRETURN
    MAXSTACK = 1
    MAXLOCALS = 1

  // access flags 0x1001
  public synthetic func_72929_e(F)F
    ALOAD 0
    GETFIELD cofh/asmhooks/world/WorldServerProxy.proxiedWorld : Lnet/minecraft/world/WorldServer;
    FLOAD 1
    INVOKEVIRTUAL net/minecraft/world/World.func_72929_e (F)F
    FRETURN
    MAXSTACK = 2
    MAXLOCALS = 2

  // access flags 0x1001
  public synthetic func_175725_q(Lnet/minecraft/util/math/BlockPos;)Lnet/minecraft/util/math/BlockPos;
    ALOAD 0
    GETFIELD cofh/asmhooks/world/WorldServerProxy.proxiedWorld : Lnet/minecraft/world/WorldServer;
    ALOAD 1
    INVOKEVIRTUAL net/minecraft/world/World.func_175725_q (Lnet/minecraft/util/math/BlockPos;)Lnet/minecraft/util/math/BlockPos;
    ARETURN
    MAXSTACK = 2
    MAXLOCALS = 2

  // access flags 0x1001
  public synthetic func_175672_r(Lnet/minecraft/util/math/BlockPos;)Lnet/minecraft/util/math/BlockPos;
    ALOAD 0
    GETFIELD cofh/asmhooks/world/WorldServerProxy.proxiedWorld : Lnet/minecraft/world/WorldServer;
    ALOAD 1
    INVOKEVIRTUAL net/minecraft/world/World.func_175672_r (Lnet/minecraft/util/math/BlockPos;)Lnet/minecraft/util/math/BlockPos;
    ARETURN
    MAXSTACK = 2
    MAXLOCALS = 2

  // access flags 0x1001
  public synthetic func_72870_g(Lnet/minecraft/entity/Entity;)V
    ALOAD 0
    GETFIELD cofh/asmhooks/world/WorldServerProxy.proxiedWorld : Lnet/minecraft/world/WorldServer;
    ALOAD 1
    INVOKEVIRTUAL net/minecraft/world/World.func_72870_g (Lnet/minecraft/entity/Entity;)V
    RETURN
    MAXSTACK = 2
    MAXLOCALS = 2

  // access flags 0x1001
  public synthetic func_175713_t(Lnet/minecraft/util/math/BlockPos;)V
    ALOAD 0
    GETFIELD cofh/asmhooks/world/WorldServerProxy.proxiedWorld : Lnet/minecraft/world/WorldServer;
    ALOAD 1
    INVOKEVIRTUAL net/minecraft/world/World.func_175713_t (Lnet/minecraft/util/math/BlockPos;)V
    RETURN
    MAXSTACK = 2
    MAXLOCALS = 2

  // access flags 0x1001
  public synthetic func_175700_a(Lnet/minecraft/tileentity/TileEntity;)Z
    ALOAD 0
    GETFIELD cofh/asmhooks/world/WorldServerProxy.proxiedWorld : Lnet/minecraft/world/WorldServer;
    ALOAD 1
    INVOKEVIRTUAL net/minecraft/world/World.func_175700_a (Lnet/minecraft/tileentity/TileEntity;)Z
    IRETURN
    MAXSTACK = 2
    MAXLOCALS = 2

  // access flags 0x1001
  public synthetic func_147448_a(Ljava/util/Collection;)V
    ALOAD 0
    GETFIELD cofh/asmhooks/world/WorldServerProxy.proxiedWorld : Lnet/minecraft/world/WorldServer;
    ALOAD 1
    INVOKEVIRTUAL net/minecraft/world/World.func_147448_a (Ljava/util/Collection;)V
    RETURN
    MAXSTACK = 2
    MAXLOCALS = 2

  // access flags 0x1001
  public synthetic getPersistentChunks()Lcom/google/common/collect/ImmutableSetMultimap;
    ALOAD 0
    GETFIELD cofh/asmhooks/world/WorldServerProxy.proxiedWorld : Lnet/minecraft/world/WorldServer;
    INVOKEVIRTUAL net/minecraft/world/World.getPersistentChunks ()Lcom/google/common/collect/ImmutableSetMultimap;
    ARETURN
    MAXSTACK = 1
    MAXLOCALS = 1

  // access flags 0x1001
  public synthetic func_72855_b(Lnet/minecraft/util/math/AxisAlignedBB;)Z
    ALOAD 0
    GETFIELD cofh/asmhooks/world/WorldServerProxy.proxiedWorld : Lnet/minecraft/world/WorldServer;
    ALOAD 1
    INVOKEVIRTUAL net/minecraft/world/World.func_72855_b (Lnet/minecraft/util/math/AxisAlignedBB;)Z
    IRETURN
    MAXSTACK = 2
    MAXLOCALS = 2

  // access flags 0x1001
  public synthetic func_72917_a(Lnet/minecraft/util/math/AxisAlignedBB;Lnet/minecraft/entity/Entity;)Z
    ALOAD 0
    GETFIELD cofh/asmhooks/world/WorldServerProxy.proxiedWorld : Lnet/minecraft/world/WorldServer;
    ALOAD 1
    ALOAD 2
    INVOKEVIRTUAL net/minecraft/world/World.func_72917_a (Lnet/minecraft/util/math/AxisAlignedBB;Lnet/minecraft/entity/Entity;)Z
    IRETURN
    MAXSTACK = 3
    MAXLOCALS = 3

  // access flags 0x1001
  public synthetic func_72829_c(Lnet/minecraft/util/math/AxisAlignedBB;)Z
    ALOAD 0
    GETFIELD cofh/asmhooks/world/WorldServerProxy.proxiedWorld : Lnet/minecraft/world/WorldServer;
    ALOAD 1
    INVOKEVIRTUAL net/minecraft/world/World.func_72829_c (Lnet/minecraft/util/math/AxisAlignedBB;)Z
    IRETURN
    MAXSTACK = 2
    MAXLOCALS = 2

  // access flags 0x1001
  public synthetic func_72953_d(Lnet/minecraft/util/math/AxisAlignedBB;)Z
    ALOAD 0
    GETFIELD cofh/asmhooks/world/WorldServerProxy.proxiedWorld : Lnet/minecraft/world/WorldServer;
    ALOAD 1
    INVOKEVIRTUAL net/minecraft/world/World.func_72953_d (Lnet/minecraft/util/math/AxisAlignedBB;)Z
    IRETURN
    MAXSTACK = 2
    MAXLOCALS = 2

  // access flags 0x1001
  public synthetic func_147470_e(Lnet/minecraft/util/math/AxisAlignedBB;)Z
    ALOAD 0
    GETFIELD cofh/asmhooks/world/WorldServerProxy.proxiedWorld : Lnet/minecraft/world/WorldServer;
    ALOAD 1
    INVOKEVIRTUAL net/minecraft/world/World.func_147470_e (Lnet/minecraft/util/math/AxisAlignedBB;)Z
    IRETURN
    MAXSTACK = 2
    MAXLOCALS = 2

  // access flags 0x1001
  public synthetic func_72918_a(Lnet/minecraft/util/math/AxisAlignedBB;Lnet/minecraft/block/material/Material;Lnet/minecraft/entity/Entity;)Z
    ALOAD 0
    GETFIELD cofh/asmhooks/world/WorldServerProxy.proxiedWorld : Lnet/minecraft/world/WorldServer;
    ALOAD 1
    ALOAD 2
    ALOAD 3
    INVOKEVIRTUAL net/minecraft/world/World.func_72918_a (Lnet/minecraft/util/math/AxisAlignedBB;Lnet/minecraft/block/material/Material;Lnet/minecraft/entity/Entity;)Z
    IRETURN
    MAXSTACK = 4
    MAXLOCALS = 4

  // access flags 0x1001
  public synthetic func_72875_a(Lnet/minecraft/util/math/AxisAlignedBB;Lnet/minecraft/block/material/Material;)Z
    ALOAD 0
    GETFIELD cofh/asmhooks/world/WorldServerProxy.proxiedWorld : Lnet/minecraft/world/WorldServer;
    ALOAD 1
    ALOAD 2
    INVOKEVIRTUAL net/minecraft/world/World.func_72875_a (Lnet/minecraft/util/math/AxisAlignedBB;Lnet/minecraft/block/material/Material;)Z
    IRETURN
    MAXSTACK = 3
    MAXLOCALS = 3

  // access flags 0x1001
  public synthetic func_72830_b(Lnet/minecraft/util/math/AxisAlignedBB;Lnet/minecraft/block/material/Material;)Z
    ALOAD 0
    GETFIELD cofh/asmhooks/world/WorldServerProxy.proxiedWorld : Lnet/minecraft/world/WorldServer;
    ALOAD 1
    ALOAD 2
    INVOKEVIRTUAL net/minecraft/world/World.func_72830_b (Lnet/minecraft/util/math/AxisAlignedBB;Lnet/minecraft/block/material/Material;)Z
    IRETURN
    MAXSTACK = 3
    MAXLOCALS = 3

  // access flags 0x1001
  public synthetic func_72876_a(Lnet/minecraft/entity/Entity;DDDFZ)Lnet/minecraft/world/Explosion;
    ALOAD 0
    GETFIELD cofh/asmhooks/world/WorldServerProxy.proxiedWorld : Lnet/minecraft/world/WorldServer;
    ALOAD 1
    DLOAD 2
    DLOAD 4
    DLOAD 6
    FLOAD 8
    ILOAD 9
    INVOKEVIRTUAL net/minecraft/world/World.func_72876_a (Lnet/minecraft/entity/Entity;DDDFZ)Lnet/minecraft/world/Explosion;
    ARETURN
    MAXSTACK = 10
    MAXLOCALS = 10

  // access flags 0x1001
  public synthetic func_72842_a(Lnet/minecraft/util/math/Vec3d;Lnet/minecraft/util/math/AxisAlignedBB;)F
    ALOAD 0
    GETFIELD cofh/asmhooks/world/WorldServerProxy.proxiedWorld : Lnet/minecraft/world/WorldServer;
    ALOAD 1
    ALOAD 2
    INVOKEVIRTUAL net/minecraft/world/World.func_72842_a (Lnet/minecraft/util/math/Vec3d;Lnet/minecraft/util/math/AxisAlignedBB;)F
    FRETURN
    MAXSTACK = 3
    MAXLOCALS = 3

  // access flags 0x1001
  public synthetic func_175719_a(Lnet/minecraft/entity/player/EntityPlayer;Lnet/minecraft/util/math/BlockPos;Lnet/minecraft/util/EnumFacing;)Z
    ALOAD 0
    GETFIELD cofh/asmhooks/world/WorldServerProxy.proxiedWorld : Lnet/minecraft/world/WorldServer;
    ALOAD 1
    ALOAD 2
    ALOAD 3
    INVOKEVIRTUAL net/minecraft/world/World.func_175719_a (Lnet/minecraft/entity/player/EntityPlayer;Lnet/minecraft/util/math/BlockPos;Lnet/minecraft/util/EnumFacing;)Z
    IRETURN
    MAXSTACK = 4
    MAXLOCALS = 4

  // access flags 0x1001
  public synthetic func_180498_a(Lnet/minecraft/entity/player/EntityPlayer;ILnet/minecraft/util/math/BlockPos;I)V
    ALOAD 0
    GETFIELD cofh/asmhooks/world/WorldServerProxy.proxiedWorld : Lnet/minecraft/world/WorldServer;
    ALOAD 1
    ILOAD 2
    ALOAD 3
    ILOAD 4
    INVOKEVIRTUAL net/minecraft/world/World.func_180498_a (Lnet/minecraft/entity/player/EntityPlayer;ILnet/minecraft/util/math/BlockPos;I)V
    RETURN
    MAXSTACK = 5
    MAXLOCALS = 5

  // access flags 0x1001
  public synthetic func_175625_s(Lnet/minecraft/util/math/BlockPos;)Lnet/minecraft/tileentity/TileEntity;
    ALOAD 0
    GETFIELD cofh/asmhooks/world/WorldServerProxy.proxiedWorld : Lnet/minecraft/world/WorldServer;
    ALOAD 1
    INVOKEVIRTUAL net/minecraft/world/World.func_175625_s (Lnet/minecraft/util/math/BlockPos;)Lnet/minecraft/tileentity/TileEntity;
    ARETURN
    MAXSTACK = 2
    MAXLOCALS = 2

  // access flags 0x1001
  public synthetic func_189508_F(Lnet/minecraft/util/math/BlockPos;)Lnet/minecraft/tileentity/TileEntity;
    ALOAD 0
    GETFIELD cofh/asmhooks/world/WorldServerProxy.proxiedWorld : Lnet/minecraft/world/WorldServer;
    ALOAD 1
    INVOKEVIRTUAL net/minecraft/world/World.func_189508_F (Lnet/minecraft/util/math/BlockPos;)Lnet/minecraft/tileentity/TileEntity;
    ARETURN
    MAXSTACK = 2
    MAXLOCALS = 2

  // access flags 0x1001
  public synthetic func_175690_a(Lnet/minecraft/util/math/BlockPos;Lnet/minecraft/tileentity/TileEntity;)V
    ALOAD 0
    GETFIELD cofh/asmhooks/world/WorldServerProxy.proxiedWorld : Lnet/minecraft/world/WorldServer;
    ALOAD 1
    ALOAD 2
    INVOKEVIRTUAL net/minecraft/world/World.func_175690_a (Lnet/minecraft/util/math/BlockPos;Lnet/minecraft/tileentity/TileEntity;)V
    RETURN
    MAXSTACK = 3
    MAXLOCALS = 3

  // access flags 0x1001
  public synthetic func_147457_a(Lnet/minecraft/tileentity/TileEntity;)V
    ALOAD 0
    GETFIELD cofh/asmhooks/world/WorldServerProxy.proxiedWorld : Lnet/minecraft/world/WorldServer;
    ALOAD 1
    INVOKEVIRTUAL net/minecraft/world/World.func_147457_a (Lnet/minecraft/tileentity/TileEntity;)V
    RETURN
    MAXSTACK = 2
    MAXLOCALS = 2

  // access flags 0x1001
  public synthetic func_175665_u(Lnet/minecraft/util/math/BlockPos;)Z
    ALOAD 0
    GETFIELD cofh/asmhooks/world/WorldServerProxy.proxiedWorld : Lnet/minecraft/world/WorldServer;
    ALOAD 1
    INVOKEVIRTUAL net/minecraft/world/World.func_175665_u (Lnet/minecraft/util/math/BlockPos;)Z
    IRETURN
    MAXSTACK = 2
    MAXLOCALS = 2

  // access flags 0x1001
  public synthetic func_175677_d(Lnet/minecraft/util/math/BlockPos;Z)Z
    ALOAD 0
    GETFIELD cofh/asmhooks/world/WorldServerProxy.proxiedWorld : Lnet/minecraft/world/WorldServer;
    ALOAD 1
    ILOAD 2
    INVOKEVIRTUAL net/minecraft/world/World.func_175677_d (Lnet/minecraft/util/math/BlockPos;Z)Z
    IRETURN
    MAXSTACK = 3
    MAXLOCALS = 3

  // access flags 0x1001
  public synthetic func_72966_v()V
    ALOAD 0
    GETFIELD cofh/asmhooks/world/WorldServerProxy.proxiedWorld : Lnet/minecraft/world/WorldServer;
    INVOKEVIRTUAL net/minecraft/world/World.func_72966_v ()V
    RETURN
    MAXSTACK = 1
    MAXLOCALS = 1

  // access flags 0x1001
  public synthetic func_72947_a()V
    ALOAD 0
    GETFIELD cofh/asmhooks/world/WorldServerProxy.proxiedWorld : Lnet/minecraft/world/WorldServer;
    INVOKEVIRTUAL net/minecraft/world/World.func_72947_a ()V
    RETURN
    MAXSTACK = 1
    MAXLOCALS = 1

  // access flags 0x1001
  public synthetic calculateInitialWeatherBody()V
    ALOAD 0
    GETFIELD cofh/asmhooks/world/WorldServerProxy.proxiedWorld : Lnet/minecraft/world/WorldServer;
    INVOKEVIRTUAL net/minecraft/world/World.calculateInitialWeatherBody ()V
    RETURN
    MAXSTACK = 1
    MAXLOCALS = 1

  // access flags 0x1001
  public synthetic updateWeatherBody()V
    ALOAD 0
    GETFIELD cofh/asmhooks/world/WorldServerProxy.proxiedWorld : Lnet/minecraft/world/WorldServer;
    INVOKEVIRTUAL net/minecraft/world/World.updateWeatherBody ()V
    RETURN
    MAXSTACK = 1
    MAXLOCALS = 1

  // access flags 0x1001
  public synthetic func_189507_a(Lnet/minecraft/util/math/BlockPos;Lnet/minecraft/block/state/IBlockState;Ljava/util/Random;)V
    ALOAD 0
    GETFIELD cofh/asmhooks/world/WorldServerProxy.proxiedWorld : Lnet/minecraft/world/WorldServer;
    ALOAD 1
    ALOAD 2
    ALOAD 3
    INVOKEVIRTUAL net/minecraft/world/World.func_189507_a (Lnet/minecraft/util/math/BlockPos;Lnet/minecraft/block/state/IBlockState;Ljava/util/Random;)V
    RETURN
    MAXSTACK = 4
    MAXLOCALS = 4

  // access flags 0x1001
  public synthetic func_175675_v(Lnet/minecraft/util/math/BlockPos;)Z
    ALOAD 0
    GETFIELD cofh/asmhooks/world/WorldServerProxy.proxiedWorld : Lnet/minecraft/world/WorldServer;
    ALOAD 1
    INVOKEVIRTUAL net/minecraft/world/World.func_175675_v (Lnet/minecraft/util/math/BlockPos;)Z
    IRETURN
    MAXSTACK = 2
    MAXLOCALS = 2

  // access flags 0x1001
  public synthetic func_175670_e(Lnet/minecraft/util/math/BlockPos;Z)Z
    ALOAD 0
    GETFIELD cofh/asmhooks/world/WorldServerProxy.proxiedWorld : Lnet/minecraft/world/WorldServer;
    ALOAD 1
    ILOAD 2
    INVOKEVIRTUAL net/minecraft/world/World.func_175670_e (Lnet/minecraft/util/math/BlockPos;Z)Z
    IRETURN
    MAXSTACK = 3
    MAXLOCALS = 3

  // access flags 0x1001
  public synthetic func_175662_w(Lnet/minecraft/util/math/BlockPos;)Z
    ALOAD 0
    GETFIELD cofh/asmhooks/world/WorldServerProxy.proxiedWorld : Lnet/minecraft/world/WorldServer;
    ALOAD 1
    INVOKEVIRTUAL net/minecraft/world/World.func_175662_w (Lnet/minecraft/util/math/BlockPos;)Z
    IRETURN
    MAXSTACK = 2
    MAXLOCALS = 2

  // access flags 0x1001
  public synthetic canBlockFreezeBody(Lnet/minecraft/util/math/BlockPos;Z)Z
    ALOAD 0
    GETFIELD cofh/asmhooks/world/WorldServerProxy.proxiedWorld : Lnet/minecraft/world/WorldServer;
    ALOAD 1
    ILOAD 2
    INVOKEVIRTUAL net/minecraft/world/World.canBlockFreezeBody (Lnet/minecraft/util/math/BlockPos;Z)Z
    IRETURN
    MAXSTACK = 3
    MAXLOCALS = 3

  // access flags 0x1001
  public synthetic func_175696_F(Lnet/minecraft/util/math/BlockPos;)Z
    ALOAD 0
    GETFIELD cofh/asmhooks/world/WorldServerProxy.proxiedWorld : Lnet/minecraft/world/WorldServer;
    ALOAD 1
    INVOKEVIRTUAL net/minecraft/world/World.func_175696_F (Lnet/minecraft/util/math/BlockPos;)Z
    IRETURN
    MAXSTACK = 2
    MAXLOCALS = 2

  // access flags 0x1001
  public synthetic func_175708_f(Lnet/minecraft/util/math/BlockPos;Z)Z
    ALOAD 0
    GETFIELD cofh/asmhooks/world/WorldServerProxy.proxiedWorld : Lnet/minecraft/world/WorldServer;
    ALOAD 1
    ILOAD 2
    INVOKEVIRTUAL net/minecraft/world/World.func_175708_f (Lnet/minecraft/util/math/BlockPos;Z)Z
    IRETURN
    MAXSTACK = 3
    MAXLOCALS = 3

  // access flags 0x1001
  public synthetic canSnowAtBody(Lnet/minecraft/util/math/BlockPos;Z)Z
    ALOAD 0
    GETFIELD cofh/asmhooks/world/WorldServerProxy.proxiedWorld : Lnet/minecraft/world/WorldServer;
    ALOAD 1
    ILOAD 2
    INVOKEVIRTUAL net/minecraft/world/World.canSnowAtBody (Lnet/minecraft/util/math/BlockPos;Z)Z
    IRETURN
    MAXSTACK = 3
    MAXLOCALS = 3

  // access flags 0x1001
  public synthetic func_175638_a(Lnet/minecraft/util/math/BlockPos;Lnet/minecraft/world/EnumSkyBlock;)I
    ALOAD 0
    GETFIELD cofh/asmhooks/world/WorldServerProxy.proxiedWorld : Lnet/minecraft/world/WorldServer;
    ALOAD 1
    ALOAD 2
    INVOKEVIRTUAL net/minecraft/world/World.func_175638_a (Lnet/minecraft/util/math/BlockPos;Lnet/minecraft/world/EnumSkyBlock;)I
    IRETURN
    MAXSTACK = 3
    MAXLOCALS = 3

  // access flags 0x1001
  public synthetic func_175674_a(Lnet/minecraft/entity/Entity;Lnet/minecraft/util/math/AxisAlignedBB;Lcom/google/common/base/Predicate;)Ljava/util/List;
    ALOAD 0
    GETFIELD cofh/asmhooks/world/WorldServerProxy.proxiedWorld : Lnet/minecraft/world/WorldServer;
    ALOAD 1
    ALOAD 2
    ALOAD 3
    INVOKEVIRTUAL net/minecraft/world/World.func_175674_a (Lnet/minecraft/entity/Entity;Lnet/minecraft/util/math/AxisAlignedBB;Lcom/google/common/base/Predicate;)Ljava/util/List;
    ARETURN
    MAXSTACK = 4
    MAXLOCALS = 4

  // access flags 0x1001
  public synthetic func_175644_a(Ljava/lang/Class;Lcom/google/common/base/Predicate;)Ljava/util/List;
    ALOAD 0
    GETFIELD cofh/asmhooks/world/WorldServerProxy.proxiedWorld : Lnet/minecraft/world/WorldServer;
    ALOAD 1
    ALOAD 2
    INVOKEVIRTUAL net/minecraft/world/World.func_175644_a (Ljava/lang/Class;Lcom/google/common/base/Predicate;)Ljava/util/List;
    ARETURN
    MAXSTACK = 3
    MAXLOCALS = 3

  // access flags 0x1001
  public synthetic func_175661_b(Ljava/lang/Class;Lcom/google/common/base/Predicate;)Ljava/util/List;
    ALOAD 0
    GETFIELD cofh/asmhooks/world/WorldServerProxy.proxiedWorld : Lnet/minecraft/world/WorldServer;
    ALOAD 1
    ALOAD 2
    INVOKEVIRTUAL net/minecraft/world/World.func_175661_b (Ljava/lang/Class;Lcom/google/common/base/Predicate;)Ljava/util/List;
    ARETURN
    MAXSTACK = 3
    MAXLOCALS = 3

  // access flags 0x1001
  public synthetic func_72872_a(Ljava/lang/Class;Lnet/minecraft/util/math/AxisAlignedBB;)Ljava/util/List;
    ALOAD 0
    GETFIELD cofh/asmhooks/world/WorldServerProxy.proxiedWorld : Lnet/minecraft/world/WorldServer;
    ALOAD 1
    ALOAD 2
    INVOKEVIRTUAL net/minecraft/world/World.func_72872_a (Ljava/lang/Class;Lnet/minecraft/util/math/AxisAlignedBB;)Ljava/util/List;
    ARETURN
    MAXSTACK = 3
    MAXLOCALS = 3

  // access flags 0x1001
  public synthetic func_175647_a(Ljava/lang/Class;Lnet/minecraft/util/math/AxisAlignedBB;Lcom/google/common/base/Predicate;)Ljava/util/List;
    ALOAD 0
    GETFIELD cofh/asmhooks/world/WorldServerProxy.proxiedWorld : Lnet/minecraft/world/WorldServer;
    ALOAD 1
    ALOAD 2
    ALOAD 3
    INVOKEVIRTUAL net/minecraft/world/World.func_175647_a (Ljava/lang/Class;Lnet/minecraft/util/math/AxisAlignedBB;Lcom/google/common/base/Predicate;)Ljava/util/List;
    ARETURN
    MAXSTACK = 4
    MAXLOCALS = 4

  // access flags 0x1001
  public synthetic func_72857_a(Ljava/lang/Class;Lnet/minecraft/util/math/AxisAlignedBB;Lnet/minecraft/entity/Entity;)Lnet/minecraft/entity/Entity;
    ALOAD 0
    GETFIELD cofh/asmhooks/world/WorldServerProxy.proxiedWorld : Lnet/minecraft/world/WorldServer;
    ALOAD 1
    ALOAD 2
    ALOAD 3
    INVOKEVIRTUAL net/minecraft/world/World.func_72857_a (Ljava/lang/Class;Lnet/minecraft/util/math/AxisAlignedBB;Lnet/minecraft/entity/Entity;)Lnet/minecraft/entity/Entity;
    ARETURN
    MAXSTACK = 4
    MAXLOCALS = 4

  // access flags 0x1001
  public synthetic func_73045_a(I)Lnet/minecraft/entity/Entity;
    ALOAD 0
    GETFIELD cofh/asmhooks/world/WorldServerProxy.proxiedWorld : Lnet/minecraft/world/WorldServer;
    ILOAD 1
    INVOKEVIRTUAL net/minecraft/world/World.func_73045_a (I)Lnet/minecraft/entity/Entity;
    ARETURN
    MAXSTACK = 2
    MAXLOCALS = 2

  // access flags 0x1001
  public synthetic func_175646_b(Lnet/minecraft/util/math/BlockPos;Lnet/minecraft/tileentity/TileEntity;)V
    ALOAD 0
    GETFIELD cofh/asmhooks/world/WorldServerProxy.proxiedWorld : Lnet/minecraft/world/WorldServer;
    ALOAD 1
    ALOAD 2
    INVOKEVIRTUAL net/minecraft/world/World.func_175646_b (Lnet/minecraft/util/math/BlockPos;Lnet/minecraft/tileentity/TileEntity;)V
    RETURN
    MAXSTACK = 3
    MAXLOCALS = 3

  // access flags 0x1001
  public synthetic func_72907_a(Ljava/lang/Class;)I
    ALOAD 0
    GETFIELD cofh/asmhooks/world/WorldServerProxy.proxiedWorld : Lnet/minecraft/world/WorldServer;
    ALOAD 1
    INVOKEVIRTUAL net/minecraft/world/World.func_72907_a (Ljava/lang/Class;)I
    IRETURN
    MAXSTACK = 2
    MAXLOCALS = 2

  // access flags 0x1001
  public synthetic func_175681_c(Ljava/util/Collection;)V
    ALOAD 0
    GETFIELD cofh/asmhooks/world/WorldServerProxy.proxiedWorld : Lnet/minecraft/world/WorldServer;
    ALOAD 1
    INVOKEVIRTUAL net/minecraft/world/World.func_175681_c (Ljava/util/Collection;)V
    RETURN
    MAXSTACK = 2
    MAXLOCALS = 2

  // access flags 0x1001
  public synthetic func_175716_a(Lnet/minecraft/block/Block;Lnet/minecraft/util/math/BlockPos;ZLnet/minecraft/util/EnumFacing;Lnet/minecraft/entity/Entity;Lnet/minecraft/item/ItemStack;)Z
    ALOAD 0
    GETFIELD cofh/asmhooks/world/WorldServerProxy.proxiedWorld : Lnet/minecraft/world/WorldServer;
    ALOAD 1
    ALOAD 2
    ILOAD 3
    ALOAD 4
    ALOAD 5
    ALOAD 6
    INVOKEVIRTUAL net/minecraft/world/World.func_175716_a (Lnet/minecraft/block/Block;Lnet/minecraft/util/math/BlockPos;ZLnet/minecraft/util/EnumFacing;Lnet/minecraft/entity/Entity;Lnet/minecraft/item/ItemStack;)Z
    IRETURN
    MAXSTACK = 7
    MAXLOCALS = 7

  // access flags 0x1001
  public synthetic func_181544_b(I)V
    ALOAD 0
    GETFIELD cofh/asmhooks/world/WorldServerProxy.proxiedWorld : Lnet/minecraft/world/WorldServer;
    ILOAD 1
    INVOKEVIRTUAL net/minecraft/world/World.func_181544_b (I)V
    RETURN
    MAXSTACK = 2
    MAXLOCALS = 2

  // access flags 0x1001
  public synthetic func_175624_G()Lnet/minecraft/world/WorldType;
    ALOAD 0
    GETFIELD cofh/asmhooks/world/WorldServerProxy.proxiedWorld : Lnet/minecraft/world/WorldServer;
    INVOKEVIRTUAL net/minecraft/world/World.func_175624_G ()Lnet/minecraft/world/WorldType;
    ARETURN
    MAXSTACK = 1
    MAXLOCALS = 1

  // access flags 0x1001
  public synthetic func_175676_y(Lnet/minecraft/util/math/BlockPos;)I
    ALOAD 0
    GETFIELD cofh/asmhooks/world/WorldServerProxy.proxiedWorld : Lnet/minecraft/world/WorldServer;
    ALOAD 1
    INVOKEVIRTUAL net/minecraft/world/World.func_175676_y (Lnet/minecraft/util/math/BlockPos;)I
    IRETURN
    MAXSTACK = 2
    MAXLOCALS = 2

  // access flags 0x1001
  public synthetic func_175709_b(Lnet/minecraft/util/math/BlockPos;Lnet/minecraft/util/EnumFacing;)Z
    ALOAD 0
    GETFIELD cofh/asmhooks/world/WorldServerProxy.proxiedWorld : Lnet/minecraft/world/WorldServer;
    ALOAD 1
    ALOAD 2
    INVOKEVIRTUAL net/minecraft/world/World.func_175709_b (Lnet/minecraft/util/math/BlockPos;Lnet/minecraft/util/EnumFacing;)Z
    IRETURN
    MAXSTACK = 3
    MAXLOCALS = 3

  // access flags 0x1001
  public synthetic func_175640_z(Lnet/minecraft/util/math/BlockPos;)Z
    ALOAD 0
    GETFIELD cofh/asmhooks/world/WorldServerProxy.proxiedWorld : Lnet/minecraft/world/WorldServer;
    ALOAD 1
    INVOKEVIRTUAL net/minecraft/world/World.func_175640_z (Lnet/minecraft/util/math/BlockPos;)Z
    IRETURN
    MAXSTACK = 2
    MAXLOCALS = 2

  // access flags 0x1001
  public synthetic func_175687_A(Lnet/minecraft/util/math/BlockPos;)I
    ALOAD 0
    GETFIELD cofh/asmhooks/world/WorldServerProxy.proxiedWorld : Lnet/minecraft/world/WorldServer;
    ALOAD 1
    INVOKEVIRTUAL net/minecraft/world/World.func_175687_A (Lnet/minecraft/util/math/BlockPos;)I
    IRETURN
    MAXSTACK = 2
    MAXLOCALS = 2

  // access flags 0x1001
  public synthetic func_72890_a(Lnet/minecraft/entity/Entity;D)Lnet/minecraft/entity/player/EntityPlayer;
    ALOAD 0
    GETFIELD cofh/asmhooks/world/WorldServerProxy.proxiedWorld : Lnet/minecraft/world/WorldServer;
    ALOAD 1
    DLOAD 2
    INVOKEVIRTUAL net/minecraft/world/World.func_72890_a (Lnet/minecraft/entity/Entity;D)Lnet/minecraft/entity/player/EntityPlayer;
    ARETURN
    MAXSTACK = 4
    MAXLOCALS = 4

  // access flags 0x1001
  public synthetic func_184137_a(DDDDZ)Lnet/minecraft/entity/player/EntityPlayer;
    ALOAD 0
    GETFIELD cofh/asmhooks/world/WorldServerProxy.proxiedWorld : Lnet/minecraft/world/WorldServer;
    DLOAD 1
    DLOAD 3
    DLOAD 5
    DLOAD 7
    ILOAD 9
    INVOKEVIRTUAL net/minecraft/world/World.func_184137_a (DDDDZ)Lnet/minecraft/entity/player/EntityPlayer;
    ARETURN
    MAXSTACK = 10
    MAXLOCALS = 10

  // access flags 0x1001
  public synthetic func_184136_b(Lnet/minecraft/entity/Entity;D)Lnet/minecraft/entity/player/EntityPlayer;
    ALOAD 0
    GETFIELD cofh/asmhooks/world/WorldServerProxy.proxiedWorld : Lnet/minecraft/world/WorldServer;
    ALOAD 1
    DLOAD 2
    INVOKEVIRTUAL net/minecraft/world/World.func_184136_b (Lnet/minecraft/entity/Entity;D)Lnet/minecraft/entity/player/EntityPlayer;
    ARETURN
    MAXSTACK = 4
    MAXLOCALS = 4

  // access flags 0x1001
  public synthetic func_175636_b(DDDD)Z
    ALOAD 0
    GETFIELD cofh/asmhooks/world/WorldServerProxy.proxiedWorld : Lnet/minecraft/world/WorldServer;
    DLOAD 1
    DLOAD 3
    DLOAD 5
    DLOAD 7
    INVOKEVIRTUAL net/minecraft/world/World.func_175636_b (DDDD)Z
    IRETURN
    MAXSTACK = 9
    MAXLOCALS = 9

  // access flags 0x1001
  public synthetic func_184142_a(Lnet/minecraft/entity/Entity;DD)Lnet/minecraft/entity/player/EntityPlayer;
    ALOAD 0
    GETFIELD cofh/asmhooks/world/WorldServerProxy.proxiedWorld : Lnet/minecraft/world/WorldServer;
    ALOAD 1
    DLOAD 2
    DLOAD 4
    INVOKEVIRTUAL net/minecraft/world/World.func_184142_a (Lnet/minecraft/entity/Entity;DD)Lnet/minecraft/entity/player/EntityPlayer;
    ARETURN
    MAXSTACK = 6
    MAXLOCALS = 6

  // access flags 0x1001
  public synthetic func_184150_a(DDDDDLcom/google/common/base/Function;Lcom/google/common/base/Predicate;)Lnet/minecraft/entity/player/EntityPlayer;
    ALOAD 0
    GETFIELD cofh/asmhooks/world/WorldServerProxy.proxiedWorld : Lnet/minecraft/world/WorldServer;
    DLOAD 1
    DLOAD 3
    DLOAD 5
    DLOAD 7
    DLOAD 9
    ALOAD 11
    ALOAD 12
    INVOKEVIRTUAL net/minecraft/world/World.func_184150_a (DDDDDLcom/google/common/base/Function;Lcom/google/common/base/Predicate;)Lnet/minecraft/entity/player/EntityPlayer;
    ARETURN
    MAXSTACK = 13
    MAXLOCALS = 13

  // access flags 0x1001
  public synthetic func_184139_a(Lnet/minecraft/util/math/BlockPos;DD)Lnet/minecraft/entity/player/EntityPlayer;
    ALOAD 0
    GETFIELD cofh/asmhooks/world/WorldServerProxy.proxiedWorld : Lnet/minecraft/world/WorldServer;
    ALOAD 1
    DLOAD 2
    DLOAD 4
    INVOKEVIRTUAL net/minecraft/world/World.func_184139_a (Lnet/minecraft/util/math/BlockPos;DD)Lnet/minecraft/entity/player/EntityPlayer;
    ARETURN
    MAXSTACK = 6
    MAXLOCALS = 6

  // access flags 0x1001
  public synthetic func_72924_a(Ljava/lang/String;)Lnet/minecraft/entity/player/EntityPlayer;
    ALOAD 0
    GETFIELD cofh/asmhooks/world/WorldServerProxy.proxiedWorld : Lnet/minecraft/world/WorldServer;
    ALOAD 1
    INVOKEVIRTUAL net/minecraft/world/World.func_72924_a (Ljava/lang/String;)Lnet/minecraft/entity/player/EntityPlayer;
    ARETURN
    MAXSTACK = 2
    MAXLOCALS = 2

  // access flags 0x1001
  public synthetic func_152378_a(Ljava/util/UUID;)Lnet/minecraft/entity/player/EntityPlayer;
    ALOAD 0
    GETFIELD cofh/asmhooks/world/WorldServerProxy.proxiedWorld : Lnet/minecraft/world/WorldServer;
    ALOAD 1
    INVOKEVIRTUAL net/minecraft/world/World.func_152378_a (Ljava/util/UUID;)Lnet/minecraft/entity/player/EntityPlayer;
    ARETURN
    MAXSTACK = 2
    MAXLOCALS = 2

  // access flags 0x1001
  public synthetic func_72906_B()V throws net/minecraft/world/MinecraftException 
    ALOAD 0
    GETFIELD cofh/asmhooks/world/WorldServerProxy.proxiedWorld : Lnet/minecraft/world/WorldServer;
    INVOKEVIRTUAL net/minecraft/world/World.func_72906_B ()V
    RETURN
    MAXSTACK = 1
    MAXLOCALS = 1

  // access flags 0x1001
  public synthetic func_72905_C()J
    ALOAD 0
    GETFIELD cofh/asmhooks/world/WorldServerProxy.proxiedWorld : Lnet/minecraft/world/WorldServer;
    INVOKEVIRTUAL net/minecraft/world/World.func_72905_C ()J
    LRETURN
    MAXSTACK = 2
    MAXLOCALS = 1

  // access flags 0x1001
  public synthetic func_72877_b(J)V
    ALOAD 0
    GETFIELD cofh/asmhooks/world/WorldServerProxy.proxiedWorld : Lnet/minecraft/world/WorldServer;
    LLOAD 1
    INVOKEVIRTUAL net/minecraft/world/World.func_72877_b (J)V
    RETURN
    MAXSTACK = 3
    MAXLOCALS = 3

  // access flags 0x1001
  public synthetic func_175652_B(Lnet/minecraft/util/math/BlockPos;)V
    ALOAD 0
    GETFIELD cofh/asmhooks/world/WorldServerProxy.proxiedWorld : Lnet/minecraft/world/WorldServer;
    ALOAD 1
    INVOKEVIRTUAL net/minecraft/world/World.func_175652_B (Lnet/minecraft/util/math/BlockPos;)V
    RETURN
    MAXSTACK = 2
    MAXLOCALS = 2

  // access flags 0x1001
  public synthetic func_72860_G()Lnet/minecraft/world/storage/ISaveHandler;
    ALOAD 0
    GETFIELD cofh/asmhooks/world/WorldServerProxy.proxiedWorld : Lnet/minecraft/world/WorldServer;
    INVOKEVIRTUAL net/minecraft/world/World.func_72860_G ()Lnet/minecraft/world/storage/ISaveHandler;
    ARETURN
    MAXSTACK = 1
    MAXLOCALS = 1

  // access flags 0x1001
  public synthetic func_72911_I()Z
    ALOAD 0
    GETFIELD cofh/asmhooks/world/WorldServerProxy.proxiedWorld : Lnet/minecraft/world/WorldServer;
    INVOKEVIRTUAL net/minecraft/world/World.func_72911_I ()Z
    IRETURN
    MAXSTACK = 1
    MAXLOCALS = 1

  // access flags 0x1001
  public synthetic func_72896_J()Z
    ALOAD 0
    GETFIELD cofh/asmhooks/world/WorldServerProxy.proxiedWorld : Lnet/minecraft/world/WorldServer;
    INVOKEVIRTUAL net/minecraft/world/World.func_72896_J ()Z
    IRETURN
    MAXSTACK = 1
    MAXLOCALS = 1

  // access flags 0x1001
  public synthetic func_180502_D(Lnet/minecraft/util/math/BlockPos;)Z
    ALOAD 0
    GETFIELD cofh/asmhooks/world/WorldServerProxy.proxiedWorld : Lnet/minecraft/world/WorldServer;
    ALOAD 1
    INVOKEVIRTUAL net/minecraft/world/World.func_180502_D (Lnet/minecraft/util/math/BlockPos;)Z
    IRETURN
    MAXSTACK = 2
    MAXLOCALS = 2

  // access flags 0x1001
  public synthetic func_175693_T()Lnet/minecraft/world/storage/MapStorage;
    ALOAD 0
    GETFIELD cofh/asmhooks/world/WorldServerProxy.proxiedWorld : Lnet/minecraft/world/WorldServer;
    INVOKEVIRTUAL net/minecraft/world/World.func_175693_T ()Lnet/minecraft/world/storage/MapStorage;
    ARETURN
    MAXSTACK = 1
    MAXLOCALS = 1

  // access flags 0x1001
  public synthetic func_72823_a(Ljava/lang/String;Lnet/minecraft/world/WorldSavedData;)V
    ALOAD 0
    GETFIELD cofh/asmhooks/world/WorldServerProxy.proxiedWorld : Lnet/minecraft/world/WorldServer;
    ALOAD 1
    ALOAD 2
    INVOKEVIRTUAL net/minecraft/world/World.func_72823_a (Ljava/lang/String;Lnet/minecraft/world/WorldSavedData;)V
    RETURN
    MAXSTACK = 3
    MAXLOCALS = 3

  // access flags 0x1001
  public synthetic func_72943_a(Ljava/lang/Class;Ljava/lang/String;)Lnet/minecraft/world/WorldSavedData;
    ALOAD 0
    GETFIELD cofh/asmhooks/world/WorldServerProxy.proxiedWorld : Lnet/minecraft/world/WorldServer;
    ALOAD 1
    ALOAD 2
    INVOKEVIRTUAL net/minecraft/world/World.func_72943_a (Ljava/lang/Class;Ljava/lang/String;)Lnet/minecraft/world/WorldSavedData;
    ARETURN
    MAXSTACK = 3
    MAXLOCALS = 3

  // access flags 0x1001
  public synthetic func_72841_b(Ljava/lang/String;)I
    ALOAD 0
    GETFIELD cofh/asmhooks/world/WorldServerProxy.proxiedWorld : Lnet/minecraft/world/WorldServer;
    ALOAD 1
    INVOKEVIRTUAL net/minecraft/world/World.func_72841_b (Ljava/lang/String;)I
    IRETURN
    MAXSTACK = 2
    MAXLOCALS = 2

  // access flags 0x1001
  public synthetic func_175669_a(ILnet/minecraft/util/math/BlockPos;I)V
    ALOAD 0
    GETFIELD cofh/asmhooks/world/WorldServerProxy.proxiedWorld : Lnet/minecraft/world/WorldServer;
    ILOAD 1
    ALOAD 2
    ILOAD 3
    INVOKEVIRTUAL net/minecraft/world/World.func_175669_a (ILnet/minecraft/util/math/BlockPos;I)V
    RETURN
    MAXSTACK = 4
    MAXLOCALS = 4

  // access flags 0x1001
  public synthetic func_72800_K()I
    ALOAD 0
    GETFIELD cofh/asmhooks/world/WorldServerProxy.proxiedWorld : Lnet/minecraft/world/WorldServer;
    INVOKEVIRTUAL net/minecraft/world/World.func_72800_K ()I
    IRETURN
    MAXSTACK = 1
    MAXLOCALS = 1

  // access flags 0x1001
  public synthetic func_72940_L()I
    ALOAD 0
    GETFIELD cofh/asmhooks/world/WorldServerProxy.proxiedWorld : Lnet/minecraft/world/WorldServer;
    INVOKEVIRTUAL net/minecraft/world/World.func_72940_L ()I
    IRETURN
    MAXSTACK = 1
    MAXLOCALS = 1

  // access flags 0x1001
  public synthetic func_72843_D(III)Ljava/util/Random;
    ALOAD 0
    GETFIELD cofh/asmhooks/world/WorldServerProxy.proxiedWorld : Lnet/minecraft/world/WorldServer;
    ILOAD 1
    ILOAD 2
    ILOAD 3
    INVOKEVIRTUAL net/minecraft/world/World.func_72843_D (III)Ljava/util/Random;
    ARETURN
    MAXSTACK = 4
    MAXLOCALS = 4

  // access flags 0x1001
  public synthetic func_175715_c(ILnet/minecraft/util/math/BlockPos;I)V
    ALOAD 0
    GETFIELD cofh/asmhooks/world/WorldServerProxy.proxiedWorld : Lnet/minecraft/world/WorldServer;
    ILOAD 1
    ALOAD 2
    ILOAD 3
    INVOKEVIRTUAL net/minecraft/world/World.func_175715_c (ILnet/minecraft/util/math/BlockPos;I)V
    RETURN
    MAXSTACK = 4
    MAXLOCALS = 4

  // access flags 0x1001
  public synthetic func_83015_S()Ljava/util/Calendar;
    ALOAD 0
    GETFIELD cofh/asmhooks/world/WorldServerProxy.proxiedWorld : Lnet/minecraft/world/WorldServer;
    INVOKEVIRTUAL net/minecraft/world/World.func_83015_S ()Ljava/util/Calendar;
    ARETURN
    MAXSTACK = 1
    MAXLOCALS = 1

  // access flags 0x1001
  public synthetic func_96441_U()Lnet/minecraft/scoreboard/Scoreboard;
    ALOAD 0
    GETFIELD cofh/asmhooks/world/WorldServerProxy.proxiedWorld : Lnet/minecraft/world/WorldServer;
    INVOKEVIRTUAL net/minecraft/world/World.func_96441_U ()Lnet/minecraft/scoreboard/Scoreboard;
    ARETURN
    MAXSTACK = 1
    MAXLOCALS = 1

  // access flags 0x1001
  public synthetic func_175649_E(Lnet/minecraft/util/math/BlockPos;)Lnet/minecraft/world/DifficultyInstance;
    ALOAD 0
    GETFIELD cofh/asmhooks/world/WorldServerProxy.proxiedWorld : Lnet/minecraft/world/WorldServer;
    ALOAD 1
    INVOKEVIRTUAL net/minecraft/world/World.func_175649_E (Lnet/minecraft/util/math/BlockPos;)Lnet/minecraft/world/DifficultyInstance;
    ARETURN
    MAXSTACK = 2
    MAXLOCALS = 2

  // access flags 0x1001
  public synthetic func_175657_ab()I
    ALOAD 0
    GETFIELD cofh/asmhooks/world/WorldServerProxy.proxiedWorld : Lnet/minecraft/world/WorldServer;
    INVOKEVIRTUAL net/minecraft/world/World.func_175657_ab ()I
    IRETURN
    MAXSTACK = 1
    MAXLOCALS = 1

  // access flags 0x1001
  public synthetic func_175692_b(I)V
    ALOAD 0
    GETFIELD cofh/asmhooks/world/WorldServerProxy.proxiedWorld : Lnet/minecraft/world/WorldServer;
    ILOAD 1
    INVOKEVIRTUAL net/minecraft/world/World.func_175692_b (I)V
    RETURN
    MAXSTACK = 2
    MAXLOCALS = 2

  // access flags 0x1001
  public synthetic func_175702_c(I)V
    ALOAD 0
    GETFIELD cofh/asmhooks/world/WorldServerProxy.proxiedWorld : Lnet/minecraft/world/WorldServer;
    ILOAD 1
    INVOKEVIRTUAL net/minecraft/world/World.func_175702_c (I)V
    RETURN
    MAXSTACK = 2
    MAXLOCALS = 2

  // access flags 0x1001
  public synthetic func_175714_ae()Lnet/minecraft/village/VillageCollection;
    ALOAD 0
    GETFIELD cofh/asmhooks/world/WorldServerProxy.proxiedWorld : Lnet/minecraft/world/WorldServer;
    INVOKEVIRTUAL net/minecraft/world/World.func_175714_ae ()Lnet/minecraft/village/VillageCollection;
    ARETURN
    MAXSTACK = 1
    MAXLOCALS = 1

  // access flags 0x1001
  public synthetic func_72916_c(II)Z
    ALOAD 0
    GETFIELD cofh/asmhooks/world/WorldServerProxy.proxiedWorld : Lnet/minecraft/world/WorldServer;
    ILOAD 1
    ILOAD 2
    INVOKEVIRTUAL net/minecraft/world/World.func_72916_c (II)Z
    IRETURN
    MAXSTACK = 3
    MAXLOCALS = 3

  // access flags 0x1001
  public synthetic isSideSolid(Lnet/minecraft/util/math/BlockPos;Lnet/minecraft/util/EnumFacing;Z)Z
    ALOAD 0
    GETFIELD cofh/asmhooks/world/WorldServerProxy.proxiedWorld : Lnet/minecraft/world/WorldServer;
    ALOAD 1
    ALOAD 2
    ILOAD 3
    INVOKEVIRTUAL net/minecraft/world/World.isSideSolid (Lnet/minecraft/util/math/BlockPos;Lnet/minecraft/util/EnumFacing;Z)Z
    IRETURN
    MAXSTACK = 4
    MAXLOCALS = 4

  // access flags 0x1001
  public synthetic isSideSolid(Lnet/minecraft/util/math/BlockPos;Lnet/minecraft/util/EnumFacing;)Z
    ALOAD 0
    GETFIELD cofh/asmhooks/world/WorldServerProxy.proxiedWorld : Lnet/minecraft/world/WorldServer;
    ALOAD 1
    ALOAD 2
    INVOKEVIRTUAL net/minecraft/world/World.isSideSolid (Lnet/minecraft/util/math/BlockPos;Lnet/minecraft/util/EnumFacing;)Z
    IRETURN
    MAXSTACK = 3
    MAXLOCALS = 3

  // access flags 0x1001
  public synthetic getPersistentChunkIterable(Ljava/util/Iterator;)Ljava/util/Iterator;
    ALOAD 0
    GETFIELD cofh/asmhooks/world/WorldServerProxy.proxiedWorld : Lnet/minecraft/world/WorldServer;
    ALOAD 1
    INVOKEVIRTUAL net/minecraft/world/World.getPersistentChunkIterable (Ljava/util/Iterator;)Ljava/util/Iterator;
    ARETURN
    MAXSTACK = 2
    MAXLOCALS = 2

  // access flags 0x1001
  public synthetic getBlockLightOpacity(Lnet/minecraft/util/math/BlockPos;)I
    ALOAD 0
    GETFIELD cofh/asmhooks/world/WorldServerProxy.proxiedWorld : Lnet/minecraft/world/WorldServer;
    ALOAD 1
    INVOKEVIRTUAL net/minecraft/world/World.getBlockLightOpacity (Lnet/minecraft/util/math/BlockPos;)I
    IRETURN
    MAXSTACK = 2
    MAXLOCALS = 2

  // access flags 0x1001
  public synthetic countEntities(Lnet/minecraft/entity/EnumCreatureType;Z)I
    ALOAD 0
    GETFIELD cofh/asmhooks/world/WorldServerProxy.proxiedWorld : Lnet/minecraft/world/WorldServer;
    ALOAD 1
    ILOAD 2
    INVOKEVIRTUAL net/minecraft/world/World.countEntities (Lnet/minecraft/entity/EnumCreatureType;Z)I
    IRETURN
    MAXSTACK = 3
    MAXLOCALS = 3

  // access flags 0x1001
  public synthetic initCapabilities()V
    ALOAD 0
    GETFIELD cofh/asmhooks/world/WorldServerProxy.proxiedWorld : Lnet/minecraft/world/WorldServer;
    INVOKEVIRTUAL net/minecraft/world/World.initCapabilities ()V
    RETURN
    MAXSTACK = 1
    MAXLOCALS = 1

  // access flags 0x1001
  public synthetic hasCapability(Lnet/minecraftforge/common/capabilities/Capability;Lnet/minecraft/util/EnumFacing;)Z
    ALOAD 0
    GETFIELD cofh/asmhooks/world/WorldServerProxy.proxiedWorld : Lnet/minecraft/world/WorldServer;
    ALOAD 1
    ALOAD 2
    INVOKEVIRTUAL net/minecraft/world/World.hasCapability (Lnet/minecraftforge/common/capabilities/Capability;Lnet/minecraft/util/EnumFacing;)Z
    IRETURN
    MAXSTACK = 3
    MAXLOCALS = 3

  // access flags 0x1001
  public synthetic getCapability(Lnet/minecraftforge/common/capabilities/Capability;Lnet/minecraft/util/EnumFacing;)Ljava/lang/Object;
    ALOAD 0
    GETFIELD cofh/asmhooks/world/WorldServerProxy.proxiedWorld : Lnet/minecraft/world/WorldServer;
    ALOAD 1
    ALOAD 2
    INVOKEVIRTUAL net/minecraft/world/World.getCapability (Lnet/minecraftforge/common/capabilities/Capability;Lnet/minecraft/util/EnumFacing;)Ljava/lang/Object;
    ARETURN
    MAXSTACK = 3
    MAXLOCALS = 3

  // access flags 0x1001
  public synthetic getPerWorldStorage()Lnet/minecraft/world/storage/MapStorage;
    ALOAD 0
    GETFIELD cofh/asmhooks/world/WorldServerProxy.proxiedWorld : Lnet/minecraft/world/WorldServer;
    INVOKEVIRTUAL net/minecraft/world/World.getPerWorldStorage ()Lnet/minecraft/world/storage/MapStorage;
    ARETURN
    MAXSTACK = 1
    MAXLOCALS = 1

  // access flags 0x1001
  public synthetic func_184135_a(Lnet/minecraft/network/Packet;)V
    ALOAD 0
    GETFIELD cofh/asmhooks/world/WorldServerProxy.proxiedWorld : Lnet/minecraft/world/WorldServer;
    ALOAD 1
    INVOKEVIRTUAL net/minecraft/world/World.func_184135_a (Lnet/minecraft/network/Packet;)V
    RETURN
    MAXSTACK = 2
    MAXLOCALS = 2

  // access flags 0x1001
  public synthetic func_184146_ak()Lnet/minecraft/world/storage/loot/LootTableManager;
    ALOAD 0
    GETFIELD cofh/asmhooks/world/WorldServerProxy.proxiedWorld : Lnet/minecraft/world/WorldServer;
    INVOKEVIRTUAL net/minecraft/world/World.func_184146_ak ()Lnet/minecraft/world/storage/loot/LootTableManager;
    ARETURN
    MAXSTACK = 1
    MAXLOCALS = 1

  // access flags 0x1001
  public synthetic func_72939_s()V
    ALOAD 0
    GETFIELD cofh/asmhooks/world/WorldServerProxy.proxiedWorld : Lnet/minecraft/world/WorldServer;
    INVOKEVIRTUAL net/minecraft/world/WorldServer.func_72939_s ()V
    RETURN
    MAXSTACK = 1
    MAXLOCALS = 1

  // access flags 0x1001
  public synthetic func_175643_b()Lnet/minecraft/world/World;
    ALOAD 0
    GETFIELD cofh/asmhooks/world/WorldServerProxy.proxiedWorld : Lnet/minecraft/world/WorldServer;
    INVOKEVIRTUAL net/minecraft/world/WorldServer.func_175643_b ()Lnet/minecraft/world/World;
    ARETURN
    MAXSTACK = 1
    MAXLOCALS = 1

  // access flags 0x1001
  public synthetic func_72963_a(Lnet/minecraft/world/WorldSettings;)V
    ALOAD 0
    GETFIELD cofh/asmhooks/world/WorldServerProxy.proxiedWorld : Lnet/minecraft/world/WorldServer;
    ALOAD 1
    INVOKEVIRTUAL net/minecraft/world/WorldServer.func_72963_a (Lnet/minecraft/world/WorldSettings;)V
    RETURN
    MAXSTACK = 2
    MAXLOCALS = 2

  // access flags 0x1001
  public synthetic func_72863_F()Lnet/minecraft/world/chunk/IChunkProvider;
    ALOAD 0
    GETFIELD cofh/asmhooks/world/WorldServerProxy.proxiedWorld : Lnet/minecraft/world/WorldServer;
    INVOKEVIRTUAL net/minecraft/world/WorldServer.func_72863_F ()Lnet/minecraft/world/chunk/IChunkProvider;
    ARETURN
    MAXSTACK = 1
    MAXLOCALS = 1

  // access flags 0x1001
  public synthetic func_72863_F()Lnet/minecraft/world/gen/ChunkProviderServer;
    ALOAD 0
    GETFIELD cofh/asmhooks/world/WorldServerProxy.proxiedWorld : Lnet/minecraft/world/WorldServer;
    INVOKEVIRTUAL net/minecraft/world/WorldServer.func_72863_F ()Lnet/minecraft/world/gen/ChunkProviderServer;
    ARETURN
    MAXSTACK = 1
    MAXLOCALS = 1

  // access flags 0x1001
  public synthetic func_72970_h()Lnet/minecraft/world/chunk/IChunkProvider;
    ALOAD 0
    GETFIELD cofh/asmhooks/world/WorldServerProxy.proxiedWorld : Lnet/minecraft/world/WorldServer;
    INVOKEVIRTUAL net/minecraft/world/WorldServer.func_72970_h ()Lnet/minecraft/world/chunk/IChunkProvider;
    ARETURN
    MAXSTACK = 1
    MAXLOCALS = 1

  // access flags 0x1001
  public synthetic func_73046_m()Lnet/minecraft/server/MinecraftServer;
    ALOAD 0
    GETFIELD cofh/asmhooks/world/WorldServerProxy.proxiedWorld : Lnet/minecraft/world/WorldServer;
    INVOKEVIRTUAL net/minecraft/world/WorldServer.func_73046_m ()Lnet/minecraft/server/MinecraftServer;
    ARETURN
    MAXSTACK = 1
    MAXLOCALS = 1

  // access flags 0x1001
  public synthetic func_175680_a(IIZ)Z
    ALOAD 0
    GETFIELD cofh/asmhooks/world/WorldServerProxy.proxiedWorld : Lnet/minecraft/world/WorldServer;
    ILOAD 1
    ILOAD 2
    ILOAD 3
    INVOKEVIRTUAL net/minecraft/world/WorldServer.func_175680_a (IIZ)Z
    IRETURN
    MAXSTACK = 4
    MAXLOCALS = 4

  // access flags 0x1001
  public synthetic func_175691_a(Lnet/minecraft/util/math/BlockPos;Lnet/minecraft/block/Block;)Z
    ALOAD 0
    GETFIELD cofh/asmhooks/world/WorldServerProxy.proxiedWorld : Lnet/minecraft/world/WorldServer;
    ALOAD 1
    ALOAD 2
    INVOKEVIRTUAL net/minecraft/world/WorldServer.func_175691_a (Lnet/minecraft/util/math/BlockPos;Lnet/minecraft/block/Block;)Z
    IRETURN
    MAXSTACK = 3
    MAXLOCALS = 3

  // access flags 0x1001
  public synthetic func_73044_a(ZLnet/minecraft/util/IProgressUpdate;)V throws net/minecraft/world/MinecraftException 
    ALOAD 0
    GETFIELD cofh/asmhooks/world/WorldServerProxy.proxiedWorld : Lnet/minecraft/world/WorldServer;
    ILOAD 1
    ALOAD 2
    INVOKEVIRTUAL net/minecraft/world/WorldServer.func_73044_a (ZLnet/minecraft/util/IProgressUpdate;)V
    RETURN
    MAXSTACK = 3
    MAXLOCALS = 3

  // access flags 0x1001
  public synthetic func_73041_k()V
    ALOAD 0
    GETFIELD cofh/asmhooks/world/WorldServerProxy.proxiedWorld : Lnet/minecraft/world/WorldServer;
    INVOKEVIRTUAL net/minecraft/world/WorldServer.func_73041_k ()V
    RETURN
    MAXSTACK = 1
    MAXLOCALS = 1

  // access flags 0x1001
  public synthetic func_73056_e()Z
    ALOAD 0
    GETFIELD cofh/asmhooks/world/WorldServerProxy.proxiedWorld : Lnet/minecraft/world/WorldServer;
    INVOKEVIRTUAL net/minecraft/world/WorldServer.func_73056_e ()Z
    IRETURN
    MAXSTACK = 1
    MAXLOCALS = 1

  // access flags 0x1001
  public synthetic func_72835_b()V
    ALOAD 0
    GETFIELD cofh/asmhooks/world/WorldServerProxy.proxiedWorld : Lnet/minecraft/world/WorldServer;
    INVOKEVIRTUAL net/minecraft/world/WorldServer.func_72835_b ()V
    RETURN
    MAXSTACK = 1
    MAXLOCALS = 1

  // access flags 0x1001
  public synthetic func_73039_n()Lnet/minecraft/entity/EntityTracker;
    ALOAD 0
    GETFIELD cofh/asmhooks/world/WorldServerProxy.proxiedWorld : Lnet/minecraft/world/WorldServer;
    INVOKEVIRTUAL net/minecraft/world/WorldServer.func_73039_n ()Lnet/minecraft/entity/EntityTracker;
    ARETURN
    MAXSTACK = 1
    MAXLOCALS = 1

  // access flags 0x1001
  public synthetic func_175733_a(Ljava/util/UUID;)Lnet/minecraft/entity/Entity;
    ALOAD 0
    GETFIELD cofh/asmhooks/world/WorldServerProxy.proxiedWorld : Lnet/minecraft/world/WorldServer;
    ALOAD 1
    INVOKEVIRTUAL net/minecraft/world/WorldServer.func_175733_a (Ljava/util/UUID;)Lnet/minecraft/entity/Entity;
    ARETURN
    MAXSTACK = 2
    MAXLOCALS = 2

  // access flags 0x1001
  public synthetic func_152345_ab()Z
    ALOAD 0
    GETFIELD cofh/asmhooks/world/WorldServerProxy.proxiedWorld : Lnet/minecraft/world/WorldServer;
    INVOKEVIRTUAL net/minecraft/world/WorldServer.func_152345_ab ()Z
    IRETURN
    MAXSTACK = 1
    MAXLOCALS = 1

  // access flags 0x1001
  public synthetic func_152344_a(Ljava/lang/Runnable;)Lcom/google/common/util/concurrent/ListenableFuture;
    ALOAD 0
    GETFIELD cofh/asmhooks/world/WorldServerProxy.proxiedWorld : Lnet/minecraft/world/WorldServer;
    ALOAD 1
    INVOKEVIRTUAL net/minecraft/world/WorldServer.func_152344_a (Ljava/lang/Runnable;)Lcom/google/common/util/concurrent/ListenableFuture;
    ARETURN
    MAXSTACK = 2
    MAXLOCALS = 2

  // access flags 0x1001
  public synthetic func_73053_d()V
    ALOAD 0
    GETFIELD cofh/asmhooks/world/WorldServerProxy.proxiedWorld : Lnet/minecraft/world/WorldServer;
    INVOKEVIRTUAL net/minecraft/world/WorldServer.func_73053_d ()V
    RETURN
    MAXSTACK = 1
    MAXLOCALS = 1

  // access flags 0x1001
  public synthetic func_147488_Z()V
    ALOAD 0
    GETFIELD cofh/asmhooks/world/WorldServerProxy.proxiedWorld : Lnet/minecraft/world/WorldServer;
    INVOKEVIRTUAL net/minecraft/world/WorldServer.func_147488_Z ()V
    RETURN
    MAXSTACK = 1
    MAXLOCALS = 1

  // access flags 0x1001
  public synthetic func_175734_a(Lnet/minecraft/entity/EnumCreatureType;Lnet/minecraft/util/math/BlockPos;)Lnet/minecraft/world/biome/Biome$SpawnListEntry;
    ALOAD 0
    GETFIELD cofh/asmhooks/world/WorldServerProxy.proxiedWorld : Lnet/minecraft/world/WorldServer;
    ALOAD 1
    ALOAD 2
    INVOKEVIRTUAL net/minecraft/world/WorldServer.func_175734_a (Lnet/minecraft/entity/EnumCreatureType;Lnet/minecraft/util/math/BlockPos;)Lnet/minecraft/world/biome/Biome$SpawnListEntry;
    ARETURN
    MAXSTACK = 3
    MAXLOCALS = 3

  // access flags 0x1001
  public synthetic func_175732_a(Lnet/minecraft/entity/EnumCreatureType;Lnet/minecraft/world/biome/Biome$SpawnListEntry;Lnet/minecraft/util/math/BlockPos;)Z
    ALOAD 0
    GETFIELD cofh/asmhooks/world/WorldServerProxy.proxiedWorld : Lnet/minecraft/world/WorldServer;
    ALOAD 1
    ALOAD 2
    ALOAD 3
    INVOKEVIRTUAL net/minecraft/world/WorldServer.func_175732_a (Lnet/minecraft/entity/EnumCreatureType;Lnet/minecraft/world/biome/Biome$SpawnListEntry;Lnet/minecraft/util/math/BlockPos;)Z
    IRETURN
    MAXSTACK = 4
    MAXLOCALS = 4

  // access flags 0x1001
  public synthetic func_73051_P()V
    ALOAD 0
    GETFIELD cofh/asmhooks/world/WorldServerProxy.proxiedWorld : Lnet/minecraft/world/WorldServer;
    INVOKEVIRTUAL net/minecraft/world/WorldServer.func_73051_P ()V
    RETURN
    MAXSTACK = 1
    MAXLOCALS = 1

  // access flags 0x1001
  public synthetic func_184162_i()V
    ALOAD 0
    GETFIELD cofh/asmhooks/world/WorldServerProxy.proxiedWorld : Lnet/minecraft/world/WorldServer;
    INVOKEVIRTUAL net/minecraft/world/WorldServer.func_184162_i ()V
    RETURN
    MAXSTACK = 1
    MAXLOCALS = 1

  // access flags 0x1001
  public synthetic func_175736_a(Lnet/minecraft/util/math/BlockPos;)Lnet/minecraft/util/math/BlockPos;
    ALOAD 0
    GETFIELD cofh/asmhooks/world/WorldServerProxy.proxiedWorld : Lnet/minecraft/world/WorldServer;
    ALOAD 1
    INVOKEVIRTUAL net/minecraft/world/WorldServer.func_175736_a (Lnet/minecraft/util/math/BlockPos;)Lnet/minecraft/util/math/BlockPos;
    ARETURN
    MAXSTACK = 2
    MAXLOCALS = 2

  // access flags 0x1001
  public synthetic func_82742_i()V
    ALOAD 0
    GETFIELD cofh/asmhooks/world/WorldServerProxy.proxiedWorld : Lnet/minecraft/world/WorldServer;
    INVOKEVIRTUAL net/minecraft/world/WorldServer.func_82742_i ()V
    RETURN
    MAXSTACK = 1
    MAXLOCALS = 1

  // access flags 0x1001
  public synthetic func_175735_ai()Z
    ALOAD 0
    GETFIELD cofh/asmhooks/world/WorldServerProxy.proxiedWorld : Lnet/minecraft/world/WorldServer;
    INVOKEVIRTUAL net/minecraft/world/WorldServer.func_175735_ai ()Z
    IRETURN
    MAXSTACK = 1
    MAXLOCALS = 1

  // access flags 0x1001
  public synthetic func_175738_ah()Z
    ALOAD 0
    GETFIELD cofh/asmhooks/world/WorldServerProxy.proxiedWorld : Lnet/minecraft/world/WorldServer;
    INVOKEVIRTUAL net/minecraft/world/WorldServer.func_175738_ah ()Z
    IRETURN
    MAXSTACK = 1
    MAXLOCALS = 1

  // access flags 0x1001
  public synthetic func_73052_b(Lnet/minecraft/world/WorldSettings;)V
    ALOAD 0
    GETFIELD cofh/asmhooks/world/WorldServerProxy.proxiedWorld : Lnet/minecraft/world/WorldServer;
    ALOAD 1
    INVOKEVIRTUAL net/minecraft/world/WorldServer.func_73052_b (Lnet/minecraft/world/WorldSettings;)V
    RETURN
    MAXSTACK = 2
    MAXLOCALS = 2

  // access flags 0x1001
  public synthetic func_175737_aj()V
    ALOAD 0
    GETFIELD cofh/asmhooks/world/WorldServerProxy.proxiedWorld : Lnet/minecraft/world/WorldServer;
    INVOKEVIRTUAL net/minecraft/world/WorldServer.func_175737_aj ()V
    RETURN
    MAXSTACK = 1
    MAXLOCALS = 1

  // access flags 0x1001
  public synthetic func_73047_i()V
    ALOAD 0
    GETFIELD cofh/asmhooks/world/WorldServerProxy.proxiedWorld : Lnet/minecraft/world/WorldServer;
    INVOKEVIRTUAL net/minecraft/world/WorldServer.func_73047_i ()V
    RETURN
    MAXSTACK = 1
    MAXLOCALS = 1

  // access flags 0x1001
  public synthetic func_180504_m()Lnet/minecraft/util/math/BlockPos;
    ALOAD 0
    GETFIELD cofh/asmhooks/world/WorldServerProxy.proxiedWorld : Lnet/minecraft/world/WorldServer;
    INVOKEVIRTUAL net/minecraft/world/WorldServer.func_180504_m ()Lnet/minecraft/util/math/BlockPos;
    ARETURN
    MAXSTACK = 1
    MAXLOCALS = 1

  // access flags 0x1001
  public synthetic func_73042_a()V throws net/minecraft/world/MinecraftException 
    ALOAD 0
    GETFIELD cofh/asmhooks/world/WorldServerProxy.proxiedWorld : Lnet/minecraft/world/WorldServer;
    INVOKEVIRTUAL net/minecraft/world/WorldServer.func_73042_a ()V
    RETURN
    MAXSTACK = 1
    MAXLOCALS = 1

  // access flags 0x1001
  public synthetic func_104140_m()V
    ALOAD 0
    GETFIELD cofh/asmhooks/world/WorldServerProxy.proxiedWorld : Lnet/minecraft/world/WorldServer;
    INVOKEVIRTUAL net/minecraft/world/WorldServer.func_104140_m ()V
    RETURN
    MAXSTACK = 1
    MAXLOCALS = 1

  // access flags 0x1001
  public synthetic func_184165_i(Lnet/minecraft/entity/Entity;)Z
    ALOAD 0
    GETFIELD cofh/asmhooks/world/WorldServerProxy.proxiedWorld : Lnet/minecraft/world/WorldServer;
    ALOAD 1
    INVOKEVIRTUAL net/minecraft/world/WorldServer.func_184165_i (Lnet/minecraft/entity/Entity;)Z
    IRETURN
    MAXSTACK = 2
    MAXLOCALS = 2

  // access flags 0x1001
  public synthetic func_147485_a(Lnet/minecraft/block/BlockEventData;)Z
    ALOAD 0
    GETFIELD cofh/asmhooks/world/WorldServerProxy.proxiedWorld : Lnet/minecraft/world/WorldServer;
    ALOAD 1
    INVOKEVIRTUAL net/minecraft/world/WorldServer.func_147485_a (Lnet/minecraft/block/BlockEventData;)Z
    IRETURN
    MAXSTACK = 2
    MAXLOCALS = 2

  // access flags 0x1001
  public synthetic func_184164_w()Lnet/minecraft/server/management/PlayerChunkMap;
    ALOAD 0
    GETFIELD cofh/asmhooks/world/WorldServerProxy.proxiedWorld : Lnet/minecraft/world/WorldServer;
    INVOKEVIRTUAL net/minecraft/world/WorldServer.func_184164_w ()Lnet/minecraft/server/management/PlayerChunkMap;
    ARETURN
    MAXSTACK = 1
    MAXLOCALS = 1

  // access flags 0x1001
  public synthetic func_85176_s()Lnet/minecraft/world/Teleporter;
    ALOAD 0
    GETFIELD cofh/asmhooks/world/WorldServerProxy.proxiedWorld : Lnet/minecraft/world/WorldServer;
    INVOKEVIRTUAL net/minecraft/world/WorldServer.func_85176_s ()Lnet/minecraft/world/Teleporter;
    ARETURN
    MAXSTACK = 1
    MAXLOCALS = 1

  // access flags 0x1001
  public synthetic func_184163_y()Lnet/minecraft/world/gen/structure/template/TemplateManager;
    ALOAD 0
    GETFIELD cofh/asmhooks/world/WorldServerProxy.proxiedWorld : Lnet/minecraft/world/WorldServer;
    INVOKEVIRTUAL net/minecraft/world/WorldServer.func_184163_y ()Lnet/minecraft/world/gen/structure/template/TemplateManager;
    ARETURN
    MAXSTACK = 1
    MAXLOCALS = 1

  // access flags 0x1081
  public transient synthetic varargs func_175739_a(Lnet/minecraft/util/EnumParticleTypes;DDDIDDDD[I)V
    ALOAD 0
    GETFIELD cofh/asmhooks/world/WorldServerProxy.proxiedWorld : Lnet/minecraft/world/WorldServer;
    ALOAD 1
    DLOAD 2
    DLOAD 4
    DLOAD 6
    ILOAD 8
    DLOAD 9
    DLOAD 11
    DLOAD 13
    DLOAD 15
    ALOAD 17
    INVOKEVIRTUAL net/minecraft/world/WorldServer.func_175739_a (Lnet/minecraft/util/EnumParticleTypes;DDDIDDDD[I)V
    RETURN
    MAXSTACK = 18
    MAXLOCALS = 18

  // access flags 0x1081
  public transient synthetic varargs func_180505_a(Lnet/minecraft/util/EnumParticleTypes;ZDDDIDDDD[I)V
    ALOAD 0
    GETFIELD cofh/asmhooks/world/WorldServerProxy.proxiedWorld : Lnet/minecraft/world/WorldServer;
    ALOAD 1
    ILOAD 2
    DLOAD 3
    DLOAD 5
    DLOAD 7
    ILOAD 9
    DLOAD 10
    DLOAD 12
    DLOAD 14
    DLOAD 16
    ALOAD 18
    INVOKEVIRTUAL net/minecraft/world/WorldServer.func_180505_a (Lnet/minecraft/util/EnumParticleTypes;ZDDDIDDDD[I)V
    RETURN
    MAXSTACK = 19
    MAXLOCALS = 19

  // access flags 0x1001
  public synthetic func_184159_a(Lnet/minecraft/entity/player/EntityPlayerMP;ZDDDLnet/minecraft/network/Packet;)V
    ALOAD 0
    GETFIELD cofh/asmhooks/world/WorldServerProxy.proxiedWorld : Lnet/minecraft/world/WorldServer;
    ALOAD 1
    ILOAD 2
    DLOAD 3
    DLOAD 5
    DLOAD 7
    ALOAD 9
    INVOKEVIRTUAL net/minecraft/world/WorldServer.func_184159_a (Lnet/minecraft/entity/player/EntityPlayerMP;ZDDDLnet/minecraft/network/Packet;)V
    RETURN
    MAXSTACK = 10
    MAXLOCALS = 10

  // access flags 0x1081
  public transient synthetic varargs func_184161_a(Lnet/minecraft/entity/player/EntityPlayerMP;Lnet/minecraft/util/EnumParticleTypes;ZDDDIDDDD[I)V
    ALOAD 0
    GETFIELD cofh/asmhooks/world/WorldServerProxy.proxiedWorld : Lnet/minecraft/world/WorldServer;
    ALOAD 1
    ALOAD 2
    ILOAD 3
    DLOAD 4
    DLOAD 6
    DLOAD 8
    ILOAD 10
    DLOAD 11
    DLOAD 13
    DLOAD 15
    DLOAD 17
    ALOAD 19
    INVOKEVIRTUAL net/minecraft/world/WorldServer.func_184161_a (Lnet/minecraft/entity/player/EntityPlayerMP;Lnet/minecraft/util/EnumParticleTypes;ZDDDIDDDD[I)V
    RETURN
    MAXSTACK = 20
    MAXLOCALS = 20

  // access flags 0x1001
  public synthetic getChunkSaveLocation()Ljava/io/File;
    ALOAD 0
    GETFIELD cofh/asmhooks/world/WorldServerProxy.proxiedWorld : Lnet/minecraft/world/WorldServer;
    INVOKEVIRTUAL net/minecraft/world/WorldServer.getChunkSaveLocation ()Ljava/io/File;
    ARETURN
    MAXSTACK = 1
    MAXLOCALS = 1

  // access flags 0x1001
  public synthetic func_72942_c(Lnet/minecraft/entity/Entity;)Z
    ALOAD 0
    GETFIELD cofh/asmhooks/world/WorldServerProxy.proxiedWorld : Lnet/minecraft/world/WorldServer;
    ALOAD 1
    INVOKEVIRTUAL net/minecraft/world/WorldServer.func_72942_c (Lnet/minecraft/entity/Entity;)Z
    IRETURN
    MAXSTACK = 2
    MAXLOCALS = 2

  // access flags 0x1001
  public synthetic func_72838_d(Lnet/minecraft/entity/Entity;)Z
    ALOAD 0
    GETFIELD cofh/asmhooks/world/WorldServerProxy.proxiedWorld : Lnet/minecraft/world/WorldServer;
    ALOAD 1
    INVOKEVIRTUAL net/minecraft/world/WorldServer.func_72838_d (Lnet/minecraft/entity/Entity;)Z
    IRETURN
    MAXSTACK = 2
    MAXLOCALS = 2

  // access flags 0x1001
  public synthetic func_72854_c()V
    ALOAD 0
    GETFIELD cofh/asmhooks/world/WorldServerProxy.proxiedWorld : Lnet/minecraft/world/WorldServer;
    INVOKEVIRTUAL net/minecraft/world/WorldServer.func_72854_c ()V
    RETURN
    MAXSTACK = 1
    MAXLOCALS = 1

  // access flags 0x1001
  public synthetic func_72923_a(Lnet/minecraft/entity/Entity;)V
    ALOAD 0
    GETFIELD cofh/asmhooks/world/WorldServerProxy.proxiedWorld : Lnet/minecraft/world/WorldServer;
    ALOAD 1
    INVOKEVIRTUAL net/minecraft/world/WorldServer.func_72923_a (Lnet/minecraft/entity/Entity;)V
    RETURN
    MAXSTACK = 2
    MAXLOCALS = 2

  // access flags 0x1001
  public synthetic func_72847_b(Lnet/minecraft/entity/Entity;)V
    ALOAD 0
    GETFIELD cofh/asmhooks/world/WorldServerProxy.proxiedWorld : Lnet/minecraft/world/WorldServer;
    ALOAD 1
    INVOKEVIRTUAL net/minecraft/world/WorldServer.func_72847_b (Lnet/minecraft/entity/Entity;)V
    RETURN
    MAXSTACK = 2
    MAXLOCALS = 2

  // access flags 0x1001
  public synthetic func_184145_b(Lnet/minecraft/util/math/BlockPos;Lnet/minecraft/block/Block;)Z
    ALOAD 0
    GETFIELD cofh/asmhooks/world/WorldServerProxy.proxiedWorld : Lnet/minecraft/world/WorldServer;
    ALOAD 1
    ALOAD 2
    INVOKEVIRTUAL net/minecraft/world/WorldServer.func_184145_b (Lnet/minecraft/util/math/BlockPos;Lnet/minecraft/block/Block;)Z
    IRETURN
    MAXSTACK = 3
    MAXLOCALS = 3

  // access flags 0x1001
  public synthetic func_175684_a(Lnet/minecraft/util/math/BlockPos;Lnet/minecraft/block/Block;I)V
    ALOAD 0
    GETFIELD cofh/asmhooks/world/WorldServerProxy.proxiedWorld : Lnet/minecraft/world/WorldServer;
    ALOAD 1
    ALOAD 2
    ILOAD 3
    INVOKEVIRTUAL net/minecraft/world/WorldServer.func_175684_a (Lnet/minecraft/util/math/BlockPos;Lnet/minecraft/block/Block;I)V
    RETURN
    MAXSTACK = 4
    MAXLOCALS = 4

  // access flags 0x1001
  public synthetic func_175654_a(Lnet/minecraft/util/math/BlockPos;Lnet/minecraft/block/Block;II)V
    ALOAD 0
    GETFIELD cofh/asmhooks/world/WorldServerProxy.proxiedWorld : Lnet/minecraft/world/WorldServer;
    ALOAD 1
    ALOAD 2
    ILOAD 3
    ILOAD 4
    INVOKEVIRTUAL net/minecraft/world/WorldServer.func_175654_a (Lnet/minecraft/util/math/BlockPos;Lnet/minecraft/block/Block;II)V
    RETURN
    MAXSTACK = 5
    MAXLOCALS = 5

  // access flags 0x1001
  public synthetic func_180497_b(Lnet/minecraft/util/math/BlockPos;Lnet/minecraft/block/Block;II)V
    ALOAD 0
    GETFIELD cofh/asmhooks/world/WorldServerProxy.proxiedWorld : Lnet/minecraft/world/WorldServer;
    ALOAD 1
    ALOAD 2
    ILOAD 3
    ILOAD 4
    INVOKEVIRTUAL net/minecraft/world/WorldServer.func_180497_b (Lnet/minecraft/util/math/BlockPos;Lnet/minecraft/block/Block;II)V
    RETURN
    MAXSTACK = 5
    MAXLOCALS = 5

  // access flags 0x1001
  public synthetic func_184147_l()V
    ALOAD 0
    GETFIELD cofh/asmhooks/world/WorldServerProxy.proxiedWorld : Lnet/minecraft/world/WorldServer;
    INVOKEVIRTUAL net/minecraft/world/WorldServer.func_184147_l ()V
    RETURN
    MAXSTACK = 1
    MAXLOCALS = 1

  // access flags 0x1001
  public synthetic func_72866_a(Lnet/minecraft/entity/Entity;Z)V
    ALOAD 0
    GETFIELD cofh/asmhooks/world/WorldServerProxy.proxiedWorld : Lnet/minecraft/world/WorldServer;
    ALOAD 1
    ILOAD 2
    INVOKEVIRTUAL net/minecraft/world/WorldServer.func_72866_a (Lnet/minecraft/entity/Entity;Z)V
    RETURN
    MAXSTACK = 3
    MAXLOCALS = 3

  // access flags 0x1001
  public synthetic func_72885_a(Lnet/minecraft/entity/Entity;DDDFZZ)Lnet/minecraft/world/Explosion;
    ALOAD 0
    GETFIELD cofh/asmhooks/world/WorldServerProxy.proxiedWorld : Lnet/minecraft/world/WorldServer;
    ALOAD 1
    DLOAD 2
    DLOAD 4
    DLOAD 6
    FLOAD 8
    ILOAD 9
    ILOAD 10
    INVOKEVIRTUAL net/minecraft/world/WorldServer.func_72885_a (Lnet/minecraft/entity/Entity;DDDFZZ)Lnet/minecraft/world/Explosion;
    ARETURN
    MAXSTACK = 11
    MAXLOCALS = 11

  // access flags 0x1001
  public synthetic func_72979_l()V
    ALOAD 0
    GETFIELD cofh/asmhooks/world/WorldServerProxy.proxiedWorld : Lnet/minecraft/world/WorldServer;
    INVOKEVIRTUAL net/minecraft/world/WorldServer.func_72979_l ()V
    RETURN
    MAXSTACK = 1
    MAXLOCALS = 1

  // access flags 0x1001
  public synthetic func_147456_g()V
    ALOAD 0
    GETFIELD cofh/asmhooks/world/WorldServerProxy.proxiedWorld : Lnet/minecraft/world/WorldServer;
    INVOKEVIRTUAL net/minecraft/world/WorldServer.func_147456_g ()V
    RETURN
    MAXSTACK = 1
    MAXLOCALS = 1

  // access flags 0x1001
  public synthetic func_72955_a(Z)Z
    ALOAD 0
    GETFIELD cofh/asmhooks/world/WorldServerProxy.proxiedWorld : Lnet/minecraft/world/WorldServer;
    ILOAD 1
    INVOKEVIRTUAL net/minecraft/world/WorldServer.func_72955_a (Z)Z
    IRETURN
    MAXSTACK = 2
    MAXLOCALS = 2

  // access flags 0x1001
  public synthetic func_72920_a(Lnet/minecraft/world/chunk/Chunk;Z)Ljava/util/List;
    ALOAD 0
    GETFIELD cofh/asmhooks/world/WorldServerProxy.proxiedWorld : Lnet/minecraft/world/WorldServer;
    ALOAD 1
    ILOAD 2
    INVOKEVIRTUAL net/minecraft/world/WorldServer.func_72920_a (Lnet/minecraft/world/chunk/Chunk;Z)Ljava/util/List;
    ARETURN
    MAXSTACK = 3
    MAXLOCALS = 3

  // access flags 0x1001
  public synthetic func_175712_a(Lnet/minecraft/world/gen/structure/StructureBoundingBox;Z)Ljava/util/List;
    ALOAD 0
    GETFIELD cofh/asmhooks/world/WorldServerProxy.proxiedWorld : Lnet/minecraft/world/WorldServer;
    ALOAD 1
    ILOAD 2
    INVOKEVIRTUAL net/minecraft/world/WorldServer.func_175712_a (Lnet/minecraft/world/gen/structure/StructureBoundingBox;Z)Ljava/util/List;
    ARETURN
    MAXSTACK = 3
    MAXLOCALS = 3

  // access flags 0x1001
  public synthetic func_175650_b(Ljava/util/Collection;)V
    ALOAD 0
    GETFIELD cofh/asmhooks/world/WorldServerProxy.proxiedWorld : Lnet/minecraft/world/WorldServer;
    ALOAD 1
    INVOKEVIRTUAL net/minecraft/world/WorldServer.func_175650_b (Ljava/util/Collection;)V
    RETURN
    MAXSTACK = 2
    MAXLOCALS = 2

  // access flags 0x1001
  public synthetic func_175660_a(Lnet/minecraft/entity/player/EntityPlayer;Lnet/minecraft/util/math/BlockPos;)Z
    ALOAD 0
    GETFIELD cofh/asmhooks/world/WorldServerProxy.proxiedWorld : Lnet/minecraft/world/WorldServer;
    ALOAD 1
    ALOAD 2
    INVOKEVIRTUAL net/minecraft/world/WorldServer.func_175660_a (Lnet/minecraft/entity/player/EntityPlayer;Lnet/minecraft/util/math/BlockPos;)Z
    IRETURN
    MAXSTACK = 3
    MAXLOCALS = 3

  // access flags 0x1001
  public synthetic canMineBlockBody(Lnet/minecraft/entity/player/EntityPlayer;Lnet/minecraft/util/math/BlockPos;)Z
    ALOAD 0
    GETFIELD cofh/asmhooks/world/WorldServerProxy.proxiedWorld : Lnet/minecraft/world/WorldServer;
    ALOAD 1
    ALOAD 2
    INVOKEVIRTUAL net/minecraft/world/WorldServer.canMineBlockBody (Lnet/minecraft/entity/player/EntityPlayer;Lnet/minecraft/util/math/BlockPos;)Z
    IRETURN
    MAXSTACK = 3
    MAXLOCALS = 3

  // access flags 0x1001
  public synthetic func_72960_a(Lnet/minecraft/entity/Entity;B)V
    ALOAD 0
    GETFIELD cofh/asmhooks/world/WorldServerProxy.proxiedWorld : Lnet/minecraft/world/WorldServer;
    ALOAD 1
    ILOAD 2
    INVOKEVIRTUAL net/minecraft/world/WorldServer.func_72960_a (Lnet/minecraft/entity/Entity;B)V
    RETURN
    MAXSTACK = 3
    MAXLOCALS = 3

  // access flags 0x1001
  public synthetic func_175641_c(Lnet/minecraft/util/math/BlockPos;Lnet/minecraft/block/Block;II)V
    ALOAD 0
    GETFIELD cofh/asmhooks/world/WorldServerProxy.proxiedWorld : Lnet/minecraft/world/WorldServer;
    ALOAD 1
    ALOAD 2
    ILOAD 3
    ILOAD 4
    INVOKEVIRTUAL net/minecraft/world/WorldServer.func_175641_c (Lnet/minecraft/util/math/BlockPos;Lnet/minecraft/block/Block;II)V
    RETURN
    MAXSTACK = 5
    MAXLOCALS = 5
}
